Workbook

Sheet Executive Summary
A1: 207 Main Street, Amagansett — Market Rent Analysis
A2: Commercial market rent assessment, effective 2026-10-07. Rent basis: annual base rent per SF, triple-net (NNN) unless labelled otherwise.
A3: Built from '207 Main Street, Amagansett — Commercial Market Rent Assessment' (research/reports). All outputs are live formulas driven by the three master inputs below.
A4: MASTER INPUTS (edit these cells; every other tab links here)
A5: Input | B5: Value | C5: Unit | D5: Provenance / source
A6: Building area | B6: 1100 | C6: SF | D6: Broker-reported, unverified: every source traces to the 2016 Douglas Elliman listing ('The one story building is 1100 sf', quoted by Patch [9]) and the former operator's memoir [18]. No government record confirms it (NYS roll has no building-area field [1]; PropertyShark 'not shown' [3]). CB 50% coverage cap on ~2,178 SF lot ≈ 1,089 SF [6].
A7: Current monthly rent | B7: 5000 | C7: $/month | D7: Client-provided. Lease type (gross vs NNN), term, escalations and whether this is the lease assigned in 2017 are Unknown.
A8: NNN load assumption | B8: 7 | C8: $/SF/yr | D8: Report-derived ESTIMATE, range $5.00–$8.75: taxes $1.38–$3.22/SF on small village buildings [68]–[71]; subject taxes ~$2.96/SF [3]; 74A taxes $4.92/SF [31]; stated all-in Amagansett NNN $8.94/SF at 2095 Montauk [42]; national benchmark $4–$8/SF [72]. Insurance/maintenance unsourced.
A10: SUBJECT PROPERTY
A11: Address | B11: 207 Main Street, Amagansett, NY 11930 (Town of East Hampton, Suffolk County); north side of Main St (NY-27), between 203 Main St and the Town parking lot at 209 Main St | F11: [2]
A12: Parcel | B12: SCTM 300-171-1-18 (print key 171.-1-18), SWIS 472489 | F12: [1][7] Grade A
A13: Owner of record | B13: Amagansett Associates, 146 Oxford Blvd, Garden City, NY 11530 (every roll year 2021–2025; also owns 203 Main St) | F13: [1][2] Grade A
A14: Property class | B14: 483 'Converted Residence' (not 421 Restaurant) | F14: [1] Grade A
A15: Building SF | B15: =TEXT($B$6,"#,##0")&" SF, one story — broker-reported (2016 Elliman listing) and memoir; unverified by any government record" -> 1,100 SF, one story — broker-reported (2016 Elliman listing) and memoir; unverified by any government record | F15: [9][18] Grade B/C
A16: Lot | B16: 0.05 acre, about 2,178 SF (could be ~1,960–2,370 SF given rounding); below the CB minimum lot area of 3,000 SF | F16: [3][11][6]
A17: Historic status | B17: Town Code ch. 255, App. A § A-5(C)(1): one of nine historic commercial buildings ('First Great Atlantic and Pacific Tea Company (The Coach Factory Store)'); alterations and signage go to the ARB | F17: [4][7] Grade A
A18: Zoning | B18: Central Business (CB), highly probable but not confirmed on a zoning map; restaurant and take-out food store permitted (P) in CB per the 2018 use table | F18: [4][5][7] Grade A
A19: Parking / patio / kitchen | B19: No on-site parking (adjoins Town lot); patio: yes; kitchen 'not much bigger than a bathroom' | F19: [2][9][18]
A20: Current operation | B20: Organic Krush (since June 2017); posted hours Fri–Mon; seasonal winter closures | F20: [19][22][24]
A21: Real estate taxes (2025-26) | B21: 3261 | F21: [3] Grade D
A22: Real estate taxes $/SF | B22: =B21/$B$6 -> 2.9645455 | F22: ESTIMATE
A24: CURRENT RENT
A25: Current monthly rent | B25: =$B$7 -> 5000 | C25: Master input
A26: Current annual rent | B26: =$B$7*12 -> 60000 | C26: Monthly × 12
A27: Current $/SF/yr | B27: =B26/$B$6 -> 54.545455 | C27: Annual ÷ SF (report: $54.55 at 1,100 SF)
A28: If gross: net-equivalent $/SF/yr | B28: =B27-$B$8 -> 47.545455 | C28: Current $/SF less NNN load (report: about $47.55)
A29: Taxes as % of current rent | B29: =B21/B26 -> 0.05435 | C29: Report: about 5.4%
A31: ESTIMATED MARKET RANGE (reconciled ESTIMATE)
A32: Measure | B32: Low | C32: Midpoint | D32: High | E32: Note
A33: $/SF/yr NNN | B33: ='Market Rent Analysis'!$B$55 -> 60 | C33: ='Market Rent Analysis'!$C$55 -> 66 | D33: ='Market Rent Analysis'!$D$55 -> 72 | E33: From Market Rent Analysis (report: $60 / $66 / $72)
A34: $/SF/yr gross-equivalent | B34: =B33+$B$8 -> 67 | C34: =C33+$B$8 -> 73 | D34: =D33+$B$8 -> 79 | E34: NNN + master NNN load
A35: Monthly rent, subject (NNN) | B35: =B33*$B$6/12 -> 5500 | C35: =C33*$B$6/12 -> 6050 | D35: =D33*$B$6/12 -> 6600 | E35: $/SF × SF ÷ 12 (report: $5,500 / $6,050 / $6,600)
A36: Annual rent, subject (NNN) | B36: =B35*12 -> 66000 | C36: =C35*12 -> 72600 | D36: =D35*12 -> 79200
A37: Monthly rent, gross-equivalent | B37: =B34*$B$6/12 -> 6141.6667 | C37: =C34*$B$6/12 -> 6691.6667 | D37: =D34*$B$6/12 -> 7241.6667
A38: Current rent vs market (NNN basis) | B38: =$B$7/B35-1 -> -0.090909091 | C38: =$B$7/C35-1 -> -0.17355372 | D38: =$B$7/D35-1 -> -0.24242424 | E38: Report: about −9% / −17% / −24%
A39: Market midpoint | B39: =C33 -> 66 | C39: =C35 -> 6050 | D39: $/SF NNN → monthly (Method B weighted $66.24, rounded)
A41: RECOMMENDED LANDLORD POSITION
A42: Position | B42: Monthly | C42: $/SF/yr (NNN) | D42: Annual | E42: % over current | F42: Basis
A43: Conservative | B43: ='Market Rent Analysis'!C74 -> 5500 | C43: =B43*12/$B$6 -> 60 | D43: =B43*12 -> 66000 | E43: =B43/$B$7-1 -> 0.1 | F43: Low end of reconciled range; lowest market-supported rent the landlord can credibly defend
A44: Fair market midpoint | B44: ='Market Rent Analysis'!C75 -> 6050 | C44: =B44*12/$B$6 -> 66 | D44: =B44*12 -> 72600 | E44: =B44/$B$7-1 -> 0.21 | F44: Method B weighted result, rounded; recommended reset target at renewal
A45: Aggressive | B45: ='Market Rent Analysis'!C76 -> 7000 | C45: =B45*12/$B$6 -> 76.363636 | D45: =B45*12 -> 84000 | E45: =B45/$B$7-1 -> 0.4 | F45: 74A Montauk Hwy adjusted indicator (only Tier 1 food-service comparable); rests on an ask with key money
A46: Report: $5,500 / $6,050 / $7,000 per month; +10% / +21% / +40% over $5,000. No market-rent factor justifies a permanent reduction below $5,000/month; any relief is better framed as temporary, documented tenant-economics relief.
A48: KEY CONCLUSION
A49: Finding | B49: =IF($B$7<B35,"BELOW MARKET",IF($B$7>D35,"ABOVE MARKET","WITHIN MARKET RANGE")) -> BELOW MARKET
A50: Conclusion | B50: ="Based on the weighted comparable analysis, estimated market rent is "&TEXT(B33,"$0")&"–"&TEXT(D33,"$0")&"/SF/year (NNN), implying "&TEXT(B35,"$#,##0")&"–"&TEXT(D35,"$#,##0")&"/month; the existing "&TEXT($B$7,"$#,##0")&"/month is approximately "&TEXT(ABS(C38),"0%")&" "&IF(C38<0,"below","above")&" the estimated market midpoint of "&TEXT(C35,"$#,##0")&"/month ("&TEXT(B27,"$0.00")&" versus "&TEXT(C33,"$0.00")&"/SF). It is about "&TEXT(ABS(B38),"0%")&IF(B38<0," below"," above")&" the low end of the range and about "&TEXT(ABS(D38),"0%")&IF(D38<0," below"," above")&" the high end." -> Based on the weighted comparable analysis, estimated market rent is $60–$72/SF/year (NNN), implying $5,500–$6,600/month; the existing $5,000/month is approximately 17% below the estimated market midpoint of $6,050/month ($54.55 versus $66.00/SF). It is about 9% below the low end of the range and about 24% below the high end.
A51: If the lease is gross | B51: ="On a gross-equivalent basis the current "&TEXT(B27,"$0.00")&"/SF compares with a gross-equivalent midpoint of "&TEXT(C34,"$0.00")&"/SF, about "&TEXT(ABS(B27/C34-1),"0%")&" below." -> On a gross-equivalent basis the current $54.55/SF compares with a gross-equivalent midpoint of $73.00/SF, about 25% below.
A52: Confidence level | B52: LOW on the precise dollar range; higher on the direction of the finding. No executed Amagansett rent is public, and the 1,100 SF area and the lease type are unverified.
A53: Date of analysis | B53: 46302
A54: Strongest landlord evidence | B54: 2016–17 key money for this exact leasehold ($625,000 ask, later $575,000; assigned 2017-06-12 after 'several serious inquiries'); 74A Montauk Hwy asks $84.81/SF NNN + $700,000 key money; 11 Indian Wells first floor asks $65/SF NNN; tight post-2020 market (Amagansett Square renewal at 'almost triple'). Weakest link: the only closed Amagansett food-service lease (2095 Montauk Hwy) is about $40/SF base.
A56: LEGEND
A57: Blue text | B57: Hardcoded input or report data (edit to test scenarios)
A58: Black text | B58: Formula calculated on the same tab
A59: Green text | B59: Link to (or formula using) another tab
A60: Yellow fill | B60: Master inputs and key assumptions: Building SF (B6), current monthly rent (B7), NNN load assumption (B8); also amortization years, size elasticity, key-money share and reconciled low/high
A61: Light-green fill | B61: Key outputs
A63: Master inputs to edit: B6 (SF), B7 (current monthly rent), B8 (NNN load). Change them and every tab recalculates.

Sheet Comparable Properties
A1: Comparable Properties — de-duplicated comparables table (23 rows)
A2: Annual base rent per SF; NNN unless labelled. Monthly, Rent/SF, NNN/CAM and Effective Rent/SF are formulas. Effective Rent/SF = Rent/SF + NNN (stated figure where the report has one, otherwise the master NNN assumption) + key money ÷ amortization years ÷ SF.
A3: Label for each row (ASK / CLOSED / EXECUTED / HISTORICAL ASK) is shown in brackets at the start of Notes, exactly as the report labels it. Tier 1 = Amagansett Main St/Montauk Hwy food service ~500–3,000 SF; Tier 2 = other Amagansett commercial; Tier 3 = other Hamptons hamlets. Score 1 (weak) to 5 (near-identical).
A4: Property | B4: Address | C4: City | D4: Property Type | E4: SF | F4: Lease Type | G4: Annual Base Rent | H4: Monthly Base Rent | I4: Rent/SF | J4: NNN/CAM | K4: Effective Rent/SF | L4: Lease Term | M4: Seasonality | N4: Date | O4: Source | P4: Source Quality | Q4: Comparability Score | R4: Tier | S4: Notes | T4: Source URL
A5: Former Coche Comedor (annual option) | B5: 74A Montauk Hwy | C5: Amagansett | D5: Turnkey restaurant, 126 seats | E5: 2830 | F5: NNN | G5: 240000 | H5: =IF(ISNUMBER(G5),G5/12,"n/a") -> 20000 | I5: =IFERROR(IF(ISNUMBER(G5),G5/E5,"n/a"),"n/a") -> 84.805654 | J5: =IF(SUMPRODUCT(($A$42:$A$42=A5)*$B$42:$B$42)>0,SUMPRODUCT(($A$42:$A$42=A5)*$B$42:$B$42)/E5,IF(AND(LEFT(F5,3)="NNN",ISNUMBER(I5)),"Not stated; master "&TEXT('Executive Summary'!$B$8,"$0.00")&" applied","Unknown")) -> Not stated; master $7.00 applied | K5: =IF(AND(ISNUMBER(I5),LEFT(F5,3)="NNN"),I5+IF(ISNUMBER(J5),J5,'Executive Summary'!$B$8)+SUMPRODUCT(($A$37:$A$39=A5)*$B$37:$B$39)/$C$31/E5,"n/a") -> 116.54064 | L5: Multi-year; Crexi shows 3 mo–10 yr (D) | M5: Annual | N5: Listed 2026-03-26; ~194 days, no cut | O5: [28][29][30][31][32] | P5: B | Q5: 3 | R5: 1 | S5: [ASK] Report row 1. SF = 2,830 main level + finished lower level. Plus $700,000 key money (ASK) incl. equipment; 31 on-site spaces; renovated 2020; central A/C. Taxes $13,919 = $4.92/SF (D); full NNN Unknown, so master NNN applied. Report's gross-equiv. column ($91.81) excludes key money; Effective Rent/SF here adds key money ÷ amortization years ÷ SF. | T5: https://hamptonscommercialre.com/properties/iconic-amagansett-restaurant-turn-key-opportunity/ | https://www.compass.com/homedetails/74-A-Montauk-Hwy-Amagansett-NY-11930/2070541251466245481_lid/ | https://www.hamptonsrealestate.com/eng/hampton-rentals/detail/524-l-526-930465/74a-montauk-highway-amagansett-ny-11930 | https://www.cityfeet.com/cont/listing/74a-montauk-hwy-amagansett-ny-11930/cs39907135 | https://www.crexi.com/lease/properties/1155311/new-york-74a-montauk-highway---iconic-amagansett-restaurant
A6: Same space (seasonal option) | B6: 74A Montauk Hwy | C6: Amagansett | D6: Turnkey restaurant (same space) | E6: 2830 | F6: Unknown | G6: Seasonal: $175,000 for May 22–Sep 15, 2026 (lapsed) | H6: =IF(ISNUMBER(G6),G6/12,"n/a") -> n/a | I6: =IFERROR(IF(ISNUMBER(G6),G6/E6,"n/a"),"n/a") -> n/a | J6: =IF(SUMPRODUCT(($A$42:$A$42=A6)*$B$42:$B$42)>0,SUMPRODUCT(($A$42:$A$42=A6)*$B$42:$B$42)/E6,IF(AND(LEFT(F6,3)="NNN",ISNUMBER(I6)),"Not stated; master "&TEXT('Executive Summary'!$B$8,"$0.00")&" applied","Unknown")) -> Unknown | K6: =IF(AND(ISNUMBER(I6),LEFT(F6,3)="NNN"),I6+IF(ISNUMBER(J6),J6,'Executive Summary'!$B$8)+SUMPRODUCT(($A$37:$A$39=A6)*$B$37:$B$39)/$C$31/E6,"n/a") -> n/a | L6: 2026 season only | M6: Seasonal | N6: 2026 | O6: [28][31] | P6: B (D for dates) | Q6: 3 | R6: 1 | S6: [ASK] Report row 2. $61.84/SF per season; annual-equiv. $82.45–$92.30 (÷0.75 to ÷0.67): see seasonal block below. Seasonal ask = 72.9% of annual ask, consistent with the 2/3–3/4 broker rule [91]. | T6: https://hamptonscommercialre.com/properties/iconic-amagansett-restaurant-turn-key-opportunity/ | https://www.cityfeet.com/cont/listing/74a-montauk-hwy-amagansett-ny-11930/cs39907135
A7: 11 Indian Wells Hwy, first floor | B7: 11 Indian Wells Hwy | C7: Amagansett | D7: Dry flex/retail, no kitchen | E7: 2480 | F7: NNN | G7: 161200 | H7: =IF(ISNUMBER(G7),G7/12,"n/a") -> 13433.333 | I7: =IFERROR(IF(ISNUMBER(G7),G7/E7,"n/a"),"n/a") -> 65 | J7: =IF(SUMPRODUCT(($A$42:$A$42=A7)*$B$42:$B$42)>0,SUMPRODUCT(($A$42:$A$42=A7)*$B$42:$B$42)/E7,IF(AND(LEFT(F7,3)="NNN",ISNUMBER(I7)),"Not stated; master "&TEXT('Executive Summary'!$B$8,"$0.00")&" applied","Unknown")) -> Not stated; master $7.00 applied | K7: =IF(AND(ISNUMBER(I7),LEFT(F7,3)="NNN"),I7+IF(ISNUMBER(J7),J7,'Executive Summary'!$B$8)+SUMPRODUCT(($A$37:$A$39=A7)*$B$37:$B$39)/$C$31/E7,"n/a") -> 72 | L7: Negotiable (Compass '1-12 months' appears a template field) | M7: Annual | N7: Published 2025-11-25; ~316 days | O7: [33][36][37] | P7: B | Q7: 3 | R7: 2 | S7: [ASK] Report row 3. Main St district; raised entry stair; shared 33-space lot; historic building [4]. NNN not stated; building taxes ~$1.31–$2.02/SF [36]. | T7: https://hamptonscommercialre.com/properties/first-floor-commercial-space/ | https://hamptonscommercialre.com/properties/premier-amagansett-commercial-assemblage-136-main-street-11-indian-wells-hwy-amagansett/ | https://www.crexi.com/lease/properties/718872/new-york-11-indian-wells-hwy
A8: 11 Indian Wells Hwy, ground level | B8: 11 Indian Wells Hwy | C8: Amagansett | D8: Lower-level flex | E8: 2877 | F8: NNN | G8: 100695 | H8: =IF(ISNUMBER(G8),G8/12,"n/a") -> 8391.25 | I8: =IFERROR(IF(ISNUMBER(G8),G8/E8,"n/a"),"n/a") -> 35 | J8: =IF(SUMPRODUCT(($A$42:$A$42=A8)*$B$42:$B$42)>0,SUMPRODUCT(($A$42:$A$42=A8)*$B$42:$B$42)/E8,IF(AND(LEFT(F8,3)="NNN",ISNUMBER(I8)),"Not stated; master "&TEXT('Executive Summary'!$B$8,"$0.00")&" applied","Unknown")) -> Not stated; master $7.00 applied | K8: =IF(AND(ISNUMBER(I8),LEFT(F8,3)="NNN"),I8+IF(ISNUMBER(J8),J8,'Executive Summary'!$B$8)+SUMPRODUCT(($A$37:$A$39=A8)*$B$37:$B$39)/$C$31/E8,"n/a") -> 42 | L8: Negotiable | M8: Annual | N8: Available 2025-04-08; ~547 days | O8: [34][36] | P8: B | Q8: 2 | R8: 2 | S8: [ASK] Report row 4. Rear-lot access; no storefront visibility. NNN not stated; building taxes ~$1.31–$2.02/SF [36]. | T8: https://hamptonscommercialre.com/properties/ground-level-commercial-offering/ | https://hamptonscommercialre.com/properties/premier-amagansett-commercial-assemblage-136-main-street-11-indian-wells-hwy-amagansett/
A9: 11 Indian Wells Hwy, second floor | B9: 11 Indian Wells Hwy | C9: Amagansett | D9: Upper-floor flex/office | E9: 2844 | F9: NNN | G9: 142200 | H9: =IF(ISNUMBER(G9),G9/12,"n/a") -> 11850 | I9: =IFERROR(IF(ISNUMBER(G9),G9/E9,"n/a"),"n/a") -> 50 | J9: =IF(SUMPRODUCT(($A$42:$A$42=A9)*$B$42:$B$42)>0,SUMPRODUCT(($A$42:$A$42=A9)*$B$42:$B$42)/E9,IF(AND(LEFT(F9,3)="NNN",ISNUMBER(I9)),"Not stated; master "&TEXT('Executive Summary'!$B$8,"$0.00")&" applied","Unknown")) -> Not stated; master $7.00 applied | K9: =IF(AND(ISNUMBER(I9),LEFT(F9,3)="NNN"),I9+IF(ISNUMBER(J9),J9,'Executive Summary'!$B$8)+SUMPRODUCT(($A$37:$A$39=A9)*$B$37:$B$39)/$C$31/E9,"n/a") -> 57 | L9: Negotiable | M9: Annual | N9: ~314 days on market | O9: [35] | P9: B | Q9: 1 | R9: 2 | S9: [ASK] Report row 5. Reference only. NNN not stated. | T9: https://hamptonscommercialre.com/properties/second-floor-amagansett-commercial-flex-space-iconic-building/
A10: 136 Main St, Unit 1 (end cap) | B10: 136 Main St | C10: Amagansett | D10: Dry retail end cap | E10: 500 | F10: NNN | G10: 96000 | H10: =IF(ISNUMBER(G10),G10/12,"n/a") -> 8000 | I10: =IFERROR(IF(ISNUMBER(G10),G10/E10,"n/a"),"n/a") -> 192 | J10: =IF(SUMPRODUCT(($A$42:$A$42=A10)*$B$42:$B$42)>0,SUMPRODUCT(($A$42:$A$42=A10)*$B$42:$B$42)/E10,IF(AND(LEFT(F10,3)="NNN",ISNUMBER(I10)),"Not stated; master "&TEXT('Executive Summary'!$B$8,"$0.00")&" applied","Unknown")) -> Not stated; master $7.00 applied | K10: =IF(AND(ISNUMBER(I10),LEFT(F10,3)="NNN"),I10+IF(ISNUMBER(J10),J10,'Executive Summary'!$B$8)+SUMPRODUCT(($A$37:$A$39=A10)*$B$37:$B$39)/$C$31/E10,"n/a") -> 199 | L10: Negotiable | M10: Annual | N10: 2025–26; broker page 404 on 2026-10-07, likely leased or withdrawn | O10: [38][39][40] | P10: D (terms); B (withdrawal) | Q10: 2 | R10: 2 | S10: [ASK (last ask)] Report row 6. Small-unit trophy outlier; EXCLUDED from the conclusion. | T10: https://www.loopnet.com/Listing/136-Main-St-Amagansett-NY/32986784/ | https://hamptonscommercialre.com/properties/retail-end-cap-prime-visibility/ | https://www.compass.com/agents/the-hamptons-commercial-real-estate-team/
A11: 136 Main St warehouse | B11: 136 Main St | C11: Amagansett | D11: Warehouse / flex | E11: 2000 | F11: Unstated | G11: 180000 | H11: =IF(ISNUMBER(G11),G11/12,"n/a") -> 15000 | I11: =IFERROR(IF(ISNUMBER(G11),G11/E11,"n/a"),"n/a") -> 90 | J11: =IF(SUMPRODUCT(($A$42:$A$42=A11)*$B$42:$B$42)>0,SUMPRODUCT(($A$42:$A$42=A11)*$B$42:$B$42)/E11,IF(AND(LEFT(F11,3)="NNN",ISNUMBER(I11)),"Not stated; master "&TEXT('Executive Summary'!$B$8,"$0.00")&" applied","Unknown")) -> Unknown | K11: =IF(AND(ISNUMBER(I11),LEFT(F11,3)="NNN"),I11+IF(ISNUMBER(J11),J11,'Executive Summary'!$B$8)+SUMPRODUCT(($A$37:$A$39=A11)*$B$37:$B$39)/$C$31/E11,"n/a") -> n/a | L11: Unknown | M11: Annual | N11: Available 2025-04-10; 'Permanently Off Market' | O11: [41] | P11: B | Q11: 1 | R11: 2 | S11: [HISTORICAL ASK] Report row 7. Not storefront or food. Lease type unstated, so no effective rent is computed (report: n/a). | T11: https://www.compass.com/listing/136-main-street-amagansett-ny-11930/1819738165409919177/
A12: 2095 Montauk Hwy restaurant | B12: 2095 Montauk Hwy | C12: Amagansett 11930 (Napeague, ~6 mi east of core) | D12: Restaurant, white box, 123 seats, double hood, 3BR apartment | E12: 4476 | F12: NNN | G12: 180000 | H12: =IF(ISNUMBER(G12),G12/12,"n/a") -> 15000 | I12: =IFERROR(IF(ISNUMBER(G12),G12/E12,"n/a"),"n/a") -> 40.214477 | J12: =IF(SUMPRODUCT(($A$42:$A$42=A12)*$B$42:$B$42)>0,SUMPRODUCT(($A$42:$A$42=A12)*$B$42:$B$42)/E12,IF(AND(LEFT(F12,3)="NNN",ISNUMBER(I12)),"Not stated; master "&TEXT('Executive Summary'!$B$8,"$0.00")&" applied","Unknown")) -> 8.9365505 | K12: =IF(AND(ISNUMBER(I12),LEFT(F12,3)="NNN"),I12+IF(ISNUMBER(J12),J12,'Executive Summary'!$B$8)+SUMPRODUCT(($A$37:$A$39=A12)*$B$37:$B$39)/$C$31/E12,"n/a") -> 49.151028 | L12: Unknown | M12: Annual lease; highly seasonal stretch | N12: Closed 2025-06-08 | O12: [42][40][43] | P12: B | Q12: 2 | R12: 2 | S12: [CLOSED] Report row 8. Compass 'Rented' 2025-06-08; price flagged 'Unverified'. Stated NNN $40,000/yr = $8.94/SF is used instead of the master assumption. Same $180,000 asked in fall 2024 [43]; Compass header shows '$180,000/mo', a display error against '$180,000/yr' in the listing text. | T12: https://www.compass.com/homedetails/2095-Montauk-Hwy-Amagansett-NY-11930/1826297907410452777_lid/ | https://www.compass.com/agents/the-hamptons-commercial-real-estate-team/ | https://behindthehedges.com/fall-2024-food-market-commercial-real-estate
A13: 519–521 Montauk Hwy | B13: 519–521 Montauk Hwy | C13: Amagansett (east of core) | D13: Former restaurant shell, seats 186 | E13: 5000 | F13: NNN | G13: Rate on request | H13: =IF(ISNUMBER(G13),G13/12,"n/a") -> n/a | I13: =IFERROR(IF(ISNUMBER(G13),G13/E13,"n/a"),"n/a") -> n/a | J13: =IF(SUMPRODUCT(($A$42:$A$42=A13)*$B$42:$B$42)>0,SUMPRODUCT(($A$42:$A$42=A13)*$B$42:$B$42)/E13,IF(AND(LEFT(F13,3)="NNN",ISNUMBER(I13)),"Not stated; master "&TEXT('Executive Summary'!$B$8,"$0.00")&" applied","Unknown")) -> Unknown | K13: =IF(AND(ISNUMBER(I13),LEFT(F13,3)="NNN"),I13+IF(ISNUMBER(J13),J13,'Executive Summary'!$B$8)+SUMPRODUCT(($A$37:$A$39=A13)*$B$37:$B$39)/$C$31/E13,"n/a") -> n/a | L13: Negotiable | M13: Annual | N13: Lease status unverified 2026; sale ask $7.95M (2023) | O13: [44][45][46] | P13: D (status); B (2023 facts) | Q13: 2 | R13: 2 | S13: [ASK] Report row 9. 80 parking spaces; vacant for years. Rate on request, so no $/SF. | T13: https://www.tenantbase.com/us/building/196079 | https://behindthehedges.com/amagansett-commercial-property-lists-8-million | https://www.cityfeet.com/cont/listing/519-521-montauk-hwy-amagansett-ny-11930/cs39871633
A14: 249 Main St, Building B pop-up | B14: 249 Main St | C14: Amagansett | D14: Pop-up retail; 1,000 SF ground + 1,000 SF basement + loft | E14: 2000 | F14: Unknown | G14: Seasonal: '50K' for May 1–Sept 2021 (ambiguous) | H14: =IF(ISNUMBER(G14),G14/12,"n/a") -> n/a | I14: =IFERROR(IF(ISNUMBER(G14),G14/E14,"n/a"),"n/a") -> n/a | J14: =IF(SUMPRODUCT(($A$42:$A$42=A14)*$B$42:$B$42)>0,SUMPRODUCT(($A$42:$A$42=A14)*$B$42:$B$42)/E14,IF(AND(LEFT(F14,3)="NNN",ISNUMBER(I14)),"Not stated; master "&TEXT('Executive Summary'!$B$8,"$0.00")&" applied","Unknown")) -> Unknown | K14: =IF(AND(ISNUMBER(I14),LEFT(F14,3)="NNN"),I14+IF(ISNUMBER(J14),J14,'Executive Summary'!$B$8)+SUMPRODUCT(($A$37:$A$39=A14)*$B$37:$B$39)/$C$31/E14,"n/a") -> n/a | L14: Season | M14: Seasonal | N14: 2021 | O14: [47] | P14: C | Q14: 2 | R14: 2 | S14: [HISTORICAL ASK] Report row 10. Main St and municipal-lot access; built 1786. $25–$50/SF per season; annual-equiv. $33–$75 (÷0.75 to ÷0.67, on 2,000 or 1,000 SF): see seasonal block below. | T14: https://www.corcoran.com/listing/for-rent/249-main-street-amagansett-ny-11930/5981523/regionId/3
A15: 17 S Edison St restaurant | B15: 17 S Edison St | C15: Montauk (downtown) | D15: Turnkey restaurant, ~126 seats incl. 18 sidewalk | E15: 2729 | F15: NNN | G15: 156000 | H15: =IF(ISNUMBER(G15),G15/12,"n/a") -> 13000 | I15: =IFERROR(IF(ISNUMBER(G15),G15/E15,"n/a"),"n/a") -> 57.163796 | J15: =IF(SUMPRODUCT(($A$42:$A$42=A15)*$B$42:$B$42)>0,SUMPRODUCT(($A$42:$A$42=A15)*$B$42:$B$42)/E15,IF(AND(LEFT(F15,3)="NNN",ISNUMBER(I15)),"Not stated; master "&TEXT('Executive Summary'!$B$8,"$0.00")&" applied","Unknown")) -> Not stated; master $7.00 applied | K15: =IF(AND(ISNUMBER(I15),LEFT(F15,3)="NNN"),I15+IF(ISNUMBER(J15),J15,'Executive Summary'!$B$8)+SUMPRODUCT(($A$37:$A$39=A15)*$B$37:$B$39)/$C$31/E15,"n/a") -> 73.324661 | L15: Not stated | M15: Annual | N15: Page modified 2026-08-16 | O15: [50] | P15: B | Q15: 3 | R15: 3 | S15: [ASK] Report row 11. Plus $250,000 key money (ASK); large kitchen, 112 SF walk-in freezer. Report's gross-equiv. ($64.16) excludes key money. | T15: https://hamptonscommercialre.com/properties/17-s-edison-st-montauk-restaurant/
A16: 53 The Circle (GreyVen) | B16: 53 The Circle | C16: East Hampton Village | D16: Luxury retail | E16: 1635 | F16: NNN | G16: 237075 | H16: =IF(ISNUMBER(G16),G16/12,"n/a") -> 19756.25 | I16: =IFERROR(IF(ISNUMBER(G16),G16/E16,"n/a"),"n/a") -> 145 | J16: =IF(SUMPRODUCT(($A$42:$A$42=A16)*$B$42:$B$42)>0,SUMPRODUCT(($A$42:$A$42=A16)*$B$42:$B$42)/E16,IF(AND(LEFT(F16,3)="NNN",ISNUMBER(I16)),"Not stated; master "&TEXT('Executive Summary'!$B$8,"$0.00")&" applied","Unknown")) -> Not stated; master $7.00 applied | K16: =IF(AND(ISNUMBER(I16),LEFT(F16,3)="NNN"),I16+IF(ISNUMBER(J16),J16,'Executive Summary'!$B$8)+SUMPRODUCT(($A$37:$A$39=A16)*$B$37:$B$39)/$C$31/E16,"n/a") -> 152 | L16: Unknown | M16: Annual | N16: 2024-05-09 | O16: [53] | P16: D (internally corroborated) | Q16: 1 | R16: 3 | S16: [EXECUTED] Report row 12. Executed per Traded.co, closed 2024-05-09. 6% × $3,959,000 sale ask = $237,540, matching the rent; trophy, EXCLUDED except as ceiling. | T16: https://traded.co/deals/new-york/retail/lease/53-the-circle-1/
A17: 53 The Circle (current ask) | B17: 53 The Circle | C17: East Hampton Village | D17: Luxury retail + storage basement | E17: 1600 | F17: NNN | G17: 240000 | H17: =IF(ISNUMBER(G17),G17/12,"n/a") -> 20000 | I17: =IFERROR(IF(ISNUMBER(G17),G17/E17,"n/a"),"n/a") -> 150 | J17: =IF(SUMPRODUCT(($A$42:$A$42=A17)*$B$42:$B$42)>0,SUMPRODUCT(($A$42:$A$42=A17)*$B$42:$B$42)/E17,IF(AND(LEFT(F17,3)="NNN",ISNUMBER(I17)),"Not stated; master "&TEXT('Executive Summary'!$B$8,"$0.00")&" applied","Unknown")) -> Not stated; master $7.00 applied | K17: =IF(AND(ISNUMBER(I17),LEFT(F17,3)="NNN"),I17+IF(ISNUMBER(J17),J17,'Executive Summary'!$B$8)+SUMPRODUCT(($A$37:$A$39=A17)*$B$37:$B$39)/$C$31/E17,"n/a") -> 157 | L17: Unknown | M17: Annual | N17: Modified 2026-01-13; April 2026 sale page cites 'The tenancy' | O17: [51][52] | P17: B | Q17: 1 | R17: 3 | S17: [ASK] Report row 13. Trophy; may have leased. | T17: https://hamptonscommercialre.com/properties/retail-storefront-in-the-core-shopping-district-of-east-hampton-village/ | https://hamptonscommercialre.com/properties/prime-east-hampton-village-retail/
A18: 32 Park Place (two units) | B18: 32 Park Pl | C18: East Hampton Village | D18: Boutique retail | E18: 778 | F18: NNN | G18: 120000 | H18: =IF(ISNUMBER(G18),G18/12,"n/a") -> 10000 | I18: =IFERROR(IF(ISNUMBER(G18),G18/E18,"n/a"),"n/a") -> 154.24165 | J18: =IF(SUMPRODUCT(($A$42:$A$42=A18)*$B$42:$B$42)>0,SUMPRODUCT(($A$42:$A$42=A18)*$B$42:$B$42)/E18,IF(AND(LEFT(F18,3)="NNN",ISNUMBER(I18)),"Not stated; master "&TEXT('Executive Summary'!$B$8,"$0.00")&" applied","Unknown")) -> Not stated; master $7.00 applied | K18: =IF(AND(ISNUMBER(I18),LEFT(F18,3)="NNN"),I18+IF(ISNUMBER(J18),J18,'Executive Summary'!$B$8)+SUMPRODUCT(($A$37:$A$39=A18)*$B$37:$B$39)/$C$31/E18,"n/a") -> 161.24165 | L18: Unknown | M18: Annual | N18: Modified 2026-02-24 | O18: [56] | P18: B | Q18: 1 | R18: 3 | S18: [ASK] Report row 14. Two units, 778 SF and 807 SF, at $120,000 each ($154.24 / $148.70/SF); this row is computed on the 778 SF unit. Luxury-adjacent; fronts the village public lot. | T18: https://hamptonscommercialre.com/properties/east-hampton-village-retail-two-boutique-units-available-for-lease/
A19: 9 Railroad Ave | B19: 9 Railroad Ave | C19: East Hampton (expanded village district) | D19: Retail gallery, ex-auto shop | E19: 3000 | F19: NNN | G19: 250000 | H19: =IF(ISNUMBER(G19),G19/12,"n/a") -> 20833.333 | I19: =IFERROR(IF(ISNUMBER(G19),G19/E19,"n/a"),"n/a") -> 83.333333 | J19: =IF(SUMPRODUCT(($A$42:$A$42=A19)*$B$42:$B$42)>0,SUMPRODUCT(($A$42:$A$42=A19)*$B$42:$B$42)/E19,IF(AND(LEFT(F19,3)="NNN",ISNUMBER(I19)),"Not stated; master "&TEXT('Executive Summary'!$B$8,"$0.00")&" applied","Unknown")) -> Not stated; master $7.00 applied | K19: =IF(AND(ISNUMBER(I19),LEFT(F19,3)="NNN"),I19+IF(ISNUMBER(J19),J19,'Executive Summary'!$B$8)+SUMPRODUCT(($A$37:$A$39=A19)*$B$37:$B$39)/$C$31/E19,"n/a") -> 90.333333 | L19: Unknown | M19: Annual | N19: Modified 2026-03-06 | O19: [57] | P19: B | Q19: 2 | R19: 3 | S19: [ASK] Report row 15. Four roll-up doors; 'ample parking'. | T19: https://hamptonscommercialre.com/properties/one-of-a-kind-retail-outlet-with-character-in-east-hampton/
A20: 70 Main St, floor 1 | B20: 70 Main St | C20: Southampton Village | D20: Dry retail, wet-use infrastructure retained | E20: 2365 | F20: NNN | G20: 355000 | H20: =IF(ISNUMBER(G20),G20/12,"n/a") -> 29583.333 | I20: =IFERROR(IF(ISNUMBER(G20),G20/E20,"n/a"),"n/a") -> 150.10571 | J20: =IF(SUMPRODUCT(($A$42:$A$42=A20)*$B$42:$B$42)>0,SUMPRODUCT(($A$42:$A$42=A20)*$B$42:$B$42)/E20,IF(AND(LEFT(F20,3)="NNN",ISNUMBER(I20)),"Not stated; master "&TEXT('Executive Summary'!$B$8,"$0.00")&" applied","Unknown")) -> Not stated; master $7.00 applied | K20: =IF(AND(ISNUMBER(I20),LEFT(F20,3)="NNN"),I20+IF(ISNUMBER(J20),J20,'Executive Summary'!$B$8)+SUMPRODUCT(($A$37:$A$39=A20)*$B$37:$B$39)/$C$31/E20,"n/a") -> 157.10571 | L20: Unknown | M20: Annual | N20: Modified 2026-08-19 | O20: [58] | P20: B | Q20: 2 | R20: 3 | S20: [ASK] Report row 16. SF = 2,365 + 1,300 basement (basement excluded from $/SF). Luxury Main St; trophy. | T20: https://hamptonscommercialre.com/properties/70-main-street-floor-1-southampton-retail-for-lease/
A21: Wainscott 900 SF | B21: Montauk Hwy ('81 Montauk Hwy' per D) | C21: Wainscott | D21: Highway boutique; 'hospitality-related use' possible | E21: 900 | F21: NNN per CityFeet (D); HCRE silent | G21: 168000 | H21: =IF(ISNUMBER(G21),G21/12,"n/a") -> 14000 | I21: =IFERROR(IF(ISNUMBER(G21),G21/E21,"n/a"),"n/a") -> 186.66667 | J21: =IF(SUMPRODUCT(($A$42:$A$42=A21)*$B$42:$B$42)>0,SUMPRODUCT(($A$42:$A$42=A21)*$B$42:$B$42)/E21,IF(AND(LEFT(F21,3)="NNN",ISNUMBER(I21)),"Not stated; master "&TEXT('Executive Summary'!$B$8,"$0.00")&" applied","Unknown")) -> Not stated; master $7.00 applied | K21: =IF(AND(ISNUMBER(I21),LEFT(F21,3)="NNN"),I21+IF(ISNUMBER(J21),J21,'Executive Summary'!$B$8)+SUMPRODUCT(($A$37:$A$39=A21)*$B$37:$B$39)/$C$31/E21,"n/a") -> 193.66667 | L21: Unknown | M21: Annual | N21: Modified 2026-08-25 | O21: [59][60] | P21: B | Q21: 1 | R21: 3 | S21: [ASK] Report row 17. Small-unit premium. | T21: https://hamptonscommercialre.com/properties/a-rare-commercial-opportunity-at-the-crossroads-of-the-hamptons-most-prestigious-corridor/ | https://www.cityfeet.com/cont/listing/81-montauk-hwy-wainscott-ny-11975/cs41480188
A22: 62 Montauk Hwy (ex-Buoy One) | B22: 62 Montauk Hwy | C22: Westhampton | D22: Restaurant, 62 parking | E22: 4400 | F22: NNN | G22: 132000 | H22: =IF(ISNUMBER(G22),G22/12,"n/a") -> 11000 | I22: =IFERROR(IF(ISNUMBER(G22),G22/E22,"n/a"),"n/a") -> 30 | J22: =IF(SUMPRODUCT(($A$42:$A$42=A22)*$B$42:$B$42)>0,SUMPRODUCT(($A$42:$A$42=A22)*$B$42:$B$42)/E22,IF(AND(LEFT(F22,3)="NNN",ISNUMBER(I22)),"Not stated; master "&TEXT('Executive Summary'!$B$8,"$0.00")&" applied","Unknown")) -> Not stated; master $7.00 applied | K22: =IF(AND(ISNUMBER(I22),LEFT(F22,3)="NNN"),I22+IF(ISNUMBER(J22),J22,'Executive Summary'!$B$8)+SUMPRODUCT(($A$37:$A$39=A22)*$B$37:$B$39)/$C$31/E22,"n/a") -> 44.954545 | L22: 'Long-term' | M22: Annual | N22: Undated | O22: [61] | P22: D | Q22: 2 | R22: 3 | S22: [ASK] Report row 18. $132,000 is year-1 rent. Plus $350,000 key money (ASK); size and parking conflict with another source. Report's gross-equiv. ($37.00) excludes key money. | T22: https://www.bizquest.com/real-estate-for-lease/premier-westhampton-restaurant-opportunity/BW2453378
A23: 2 Main St | B23: 2 Main St | C23: Sag Harbor | D23: Small boutique | E23: 744 | F23: NNN | G23: 120000 | H23: =IF(ISNUMBER(G23),G23/12,"n/a") -> 10000 | I23: =IFERROR(IF(ISNUMBER(G23),G23/E23,"n/a"),"n/a") -> 161.29032 | J23: =IF(SUMPRODUCT(($A$42:$A$42=A23)*$B$42:$B$42)>0,SUMPRODUCT(($A$42:$A$42=A23)*$B$42:$B$42)/E23,IF(AND(LEFT(F23,3)="NNN",ISNUMBER(I23)),"Not stated; master "&TEXT('Executive Summary'!$B$8,"$0.00")&" applied","Unknown")) -> Not stated; master $7.00 applied | K23: =IF(AND(ISNUMBER(I23),LEFT(F23,3)="NNN"),I23+IF(ISNUMBER(J23),J23,'Executive Summary'!$B$8)+SUMPRODUCT(($A$37:$A$39=A23)*$B$37:$B$39)/$C$31/E23,"n/a") -> 168.29032 | L23: Negotiable | M23: Annual | N23: Modified 2026-09-13 | O23: [62] | P23: B | Q23: 1 | R23: 3 | S23: [ASK] Report row 19. Supporting; small-unit. | T23: https://hamptonscommercialre.com/properties/high-visibility-boutique-space/
A24: 117 Main St | B24: 117 Main St | C24: Sag Harbor | D24: Small storefront with patio | E24: 400 | F24: NNN | G24: 96000 | H24: =IF(ISNUMBER(G24),G24/12,"n/a") -> 8000 | I24: =IFERROR(IF(ISNUMBER(G24),G24/E24,"n/a"),"n/a") -> 240 | J24: =IF(SUMPRODUCT(($A$42:$A$42=A24)*$B$42:$B$42)>0,SUMPRODUCT(($A$42:$A$42=A24)*$B$42:$B$42)/E24,IF(AND(LEFT(F24,3)="NNN",ISNUMBER(I24)),"Not stated; master "&TEXT('Executive Summary'!$B$8,"$0.00")&" applied","Unknown")) -> Not stated; master $7.00 applied | K24: =IF(AND(ISNUMBER(I24),LEFT(F24,3)="NNN"),I24+IF(ISNUMBER(J24),J24,'Executive Summary'!$B$8)+SUMPRODUCT(($A$37:$A$39=A24)*$B$37:$B$39)/$C$31/E24,"n/a") -> 247 | L24: 1 year (Oct 2026–Oct 2027) | M24: Annual | N24: Modified 2026-07-23 | O24: [63] | P24: B | Q24: 1 | R24: 3 | S24: [ASK] Report row 20. SF approximate (~400). Trophy small-unit; EXCLUDED. | T24: https://hamptonscommercialre.com/properties/sag-harbor-main-street-retail/
A25: 7 Hill St (inline) | B25: 7 Hill St | C25: Southampton Village | D25: Inline retail; 'modified wet uses such as salon or ice cream' | E25: 925 | F25: NNN | G25: 66000 | H25: =IF(ISNUMBER(G25),G25/12,"n/a") -> 5500 | I25: =IFERROR(IF(ISNUMBER(G25),G25/E25,"n/a"),"n/a") -> 71.351351 | J25: =IF(SUMPRODUCT(($A$42:$A$42=A25)*$B$42:$B$42)>0,SUMPRODUCT(($A$42:$A$42=A25)*$B$42:$B$42)/E25,IF(AND(LEFT(F25,3)="NNN",ISNUMBER(I25)),"Not stated; master "&TEXT('Executive Summary'!$B$8,"$0.00")&" applied","Unknown")) -> Not stated; master $7.00 applied | K25: =IF(AND(ISNUMBER(I25),LEFT(F25,3)="NNN"),I25+IF(ISNUMBER(J25),J25,'Executive Summary'!$B$8)+SUMPRODUCT(($A$37:$A$39=A25)*$B$37:$B$39)/$C$31/E25,"n/a") -> 78.351351 | L25: Unknown | M25: Annual | N25: Modified 2026-09-18 | O25: [64][65] | P25: B (conflict) | Q25: 2 | R25: 3 | S25: [ASK] Report row 21. Combined-unit page implies $84,000 ($90.81/SF); report uses the lower $66,000. Closest size match among food-capable Tier 3 units. | T25: https://hamptonscommercialre.com/properties/inline-retail-store-in-southamptons-cultural-hub/ | https://hamptonscommercialre.com/properties/1-windmill-lane-7-hill-st-southampton/
A26: 15 Hill St, Unit B | B26: 15 Hill St | C26: Southampton Village | D26: Grocery, modified cooking | E26: 3100 | F26: NNN | G26: 240000 | H26: =IF(ISNUMBER(G26),G26/12,"n/a") -> 20000 | I26: =IFERROR(IF(ISNUMBER(G26),G26/E26,"n/a"),"n/a") -> 77.419355 | J26: =IF(SUMPRODUCT(($A$42:$A$42=A26)*$B$42:$B$42)>0,SUMPRODUCT(($A$42:$A$42=A26)*$B$42:$B$42)/E26,IF(AND(LEFT(F26,3)="NNN",ISNUMBER(I26)),"Not stated; master "&TEXT('Executive Summary'!$B$8,"$0.00")&" applied","Unknown")) -> Not stated; master $7.00 applied | K26: =IF(AND(ISNUMBER(I26),LEFT(F26,3)="NNN"),I26+IF(ISNUMBER(J26),J26,'Executive Summary'!$B$8)+SUMPRODUCT(($A$37:$A$39=A26)*$B$37:$B$39)/$C$31/E26,"n/a") -> 84.419355 | L26: Unknown | M26: Annual | N26: Modified 2026-09-28 | O26: [66] | P26: B | Q26: 2 | R26: 3 | S26: [ASK] Report row 22. Food-adjacent. | T26: https://hamptonscommercialre.com/properties/southampton-village-grocery-opportunity-at-15-hill-street-unit-b-southampton-ny/
A27: 87 North Rd bar/restaurant | B27: 87 North Rd | C27: Shinnecock Hills / Hampton Bays | D27: Bar/restaurant with kitchen | E27: 1700 | F27: Unstated | G27: 78000 | H27: =IF(ISNUMBER(G27),G27/12,"n/a") -> 6500 | I27: =IFERROR(IF(ISNUMBER(G27),G27/E27,"n/a"),"n/a") -> 45.882353 | J27: =IF(SUMPRODUCT(($A$42:$A$42=A27)*$B$42:$B$42)>0,SUMPRODUCT(($A$42:$A$42=A27)*$B$42:$B$42)/E27,IF(AND(LEFT(F27,3)="NNN",ISNUMBER(I27)),"Not stated; master "&TEXT('Executive Summary'!$B$8,"$0.00")&" applied","Unknown")) -> Unknown | K27: =IF(AND(ISNUMBER(I27),LEFT(F27,3)="NNN"),I27+IF(ISNUMBER(J27),J27,'Executive Summary'!$B$8)+SUMPRODUCT(($A$37:$A$39=A27)*$B$37:$B$39)/$C$31/E27,"n/a") -> n/a | L27: Unknown | M27: Unknown | N27: 2024-05-18 | O27: [67] | P27: B | Q27: 2 | R27: 3 | S27: [ASK] Report row 23. Peripheral Southampton Town location. Lease type unstated, so no effective rent is computed (report: Unknown). | T27: https://behindthehedges.com/bar-restaurant-available-lease-highly-visible/
A30: SUPPLEMENTARY INPUTS (referenced by the formulas above)
A31: Key-money amortization period (years) | C31: 10 | D31: Report convention 7: key money converted straight-line over an assumed 10-year term. Used in Effective Rent/SF and in the Adjustments key-money check.
A32: Seasonal share of annual rent, low (two-thirds) | C32: 0.67 | D32: Broker rule: a 4–6 month season costs 'two-thirds to three-fourths of the annual asking rent' [91]; 74A's 2026 asks confirm (72.9%) [28].
A33: Seasonal share of annual rent, high (three-fourths) | C33: 0.75
A34: Seasonal share, midpoint (used in Adjustments) | C34: =AVERAGE(C32:C33) -> 0.71 | D34: Report divides seasonal rent by 0.71 (midpoint) to reach an annual equivalent.
A36: Property (key money) | B36: Key money ($, ASK) | C36: Source | D36: Key money $/SF/yr | E36: Note
A37: =A5 -> Former Coche Comedor (annual option) | B37: 700000 | C37: [28] | D37: =B37/$C$31/E5 -> 24.734982 | E37: Includes ownership of all equipment [28]
A38: =A15 -> 17 S Edison St restaurant | B38: 250000 | C38: [50] | D38: =B38/$C$31/E15 -> 9.1608648 | E38: Turnkey restaurant
A39: =A22 -> 62 Montauk Hwy (ex-Buoy One) | B39: 350000 | C39: [61] | D39: =B39/$C$31/E22 -> 7.9545455 | E39: D-grade source
A41: Property (stated NNN) | B41: Stated NNN ($/yr) | C41: Source | D41: Stated NNN $/SF | E41: Note
A42: =A12 -> 2095 Montauk Hwy restaurant | B42: 40000 | C42: [42] | D42: =B42/E12 -> 8.9365505 | E42: '$180,000 base plus $40,000 NNN' (Compass, closed 2025-06-08)
A44: Property (seasonal) | B44: Seasonal rent ($) | C44: Season | D44: SF basis (low) | E44: SF basis (high) | F44: $/SF per season (low) | G44: $/SF per season (high) | H44: Annual-equiv. $/SF low (÷0.75) | I44: Annual-equiv. $/SF high (÷0.67)
A45: =A6 -> Same space (seasonal option) | B45: 175000 | C45: May 22–Sep 15, 2026 | D45: 2830 | E45: 2830 | F45: =B45/E45 -> 61.837456 | G45: =B45/D45 -> 61.837456 | H45: =F45/$C$33 -> 82.449941 | I45: =G45/$C$32 -> 92.29471
A46: =A14 -> 249 Main St, Building B pop-up | B46: 50000 | C46: May 1–Sept 2021 | D46: 1000 | E46: 2000 | F46: =B46/E46 -> 25 | G46: =B46/D46 -> 50 | H46: =F46/$C$33 -> 33.333333 | I46: =G46/$C$32 -> 74.626866
A47: 74A seasonal ask as % of annual ask | C47: =B45/G5 -> 0.72916667 | D47: Report: 72.9%, consistent with the 2/3–3/4 broker rule [91]. 249 Main SF basis: 2,000 SF total or 1,000 SF ground floor.
A50: NOTES & SOURCES
A51: Asking vs executed: most figures in this workbook are ASKING rents on listings, not executed leases. No executed Amagansett commercial rent is publicly disclosed for 2014–2026. The only closed Amagansett-ZIP food-service lease (2095 Montauk Hwy, closed 2025-06-08) is broker-reported and Compass flags its price 'Unverified' [42]. Asks are converted to an achieved basis with a moderate 5–10% discount (asks on market >180 days without a cut −10%; other asks −5%; closed 0%). Trophy village rows ($145–$240/SF) are excluded from the conclusion except as an outer ceiling.
A52: NNN assumption ($7.00/SF, range $5.00–$8.75; master input on Executive Summary): real estate taxes from broker-published tax bills run $1.38–$3.22/SF on small village commercial buildings [68][69][70][71]; the subject's own taxes are about $2.96/SF [3]; taxes alone at 74A are $4.92/SF [31]; the one stated all-in Amagansett NNN figure is $8.94/SF at 2095 Montauk Highway [42]; taxes at 136 Main / 11 Indian Wells run about $1.31–$2.02/SF [36]; and a generic national benchmark puts retail NNN at $4–$8/SF [72]. Insurance and maintenance components (about $1.00–$2.50 and $1.00–$3.00/SF respectively) are unsourced assumptions and should be replaced with the subject's actual figures.
A53: Labels: ASK = asking rent on a listing; EXECUTED/CLOSED = signed, assigned or broker-reported closed lease; HISTORICAL = dated past listing or event; BROKER OPINION = broker's quoted range; ESTIMATE = figure inferred or calculated in the report. Grades: A = government record or recorded transaction; B = broker listing with detailed terms or established real estate publication; C = historical listing, local newspaper or business website; D = aggregator, unverified database or search snippet.
A54: Source: '207 Main Street, Amagansett — Commercial Market Rent Assessment', effective 2026-10-07 (research/reports/207 Main Street Amagansett market rent.md). Bracketed numbers refer to the Sources tab, which lists every URL (all accessed 2026-10-07).

Sheet Executed Transactions
A1: Executed Transactions — executed / closed items only
A2: No executed Amagansett commercial rent is publicly disclosed for 2014–2026.
A3: Same columns as Comparable Properties. Rows for 2095 Montauk Hwy and GreyVen link to the Comparable Properties tab (green). About 45 searches and 30 page fetches (press archives, broker closed-deal pages, Traded.co, court, SEC and County Clerk records) found no other disclosed rent.
A4: Property | B4: Address | C4: City | D4: Property Type | E4: SF | F4: Lease Type | G4: Annual Base Rent | H4: Monthly Base Rent | I4: Rent/SF | J4: NNN/CAM | K4: Effective Rent/SF | L4: Lease Term | M4: Seasonality | N4: Date | O4: Source | P4: Source Quality | Q4: Comparability Score | R4: Tier | S4: Notes | T4: Source URL
A5: 207 Main St lease assignment (Mary's Marvelous → Organic Krush) — SUBJECT | B5: 207 Main St | C5: Amagansett | D5: Café / bakery storefront with kitchen and patio | E5: ='Executive Summary'!$B$6 -> 1100 | F5: Unknown ('long-term lease') | G5: Undisclosed | H5: =IF(ISNUMBER(G5),G5/12,"n/a") -> n/a | I5: =IFERROR(IF(ISNUMBER(G5),G5/E5,"n/a"),"n/a") -> n/a | J5: =IF(AND(LEFT(F5,3)="NNN",ISNUMBER(I5)),"Not stated; master "&TEXT('Executive Summary'!$B$8,"$0.00")&" applied","Unknown") -> Unknown | K5: =IF(AND(ISNUMBER(I5),LEFT(F5,3)="NNN"),I5+'Executive Summary'!$B$8,"n/a") -> n/a | L5: Long-term; remaining term undisclosed | M5: Annual (seasonal winter closures) | N5: Closed 2017-06-12 | O5: [10][13][15] | P5: B (broker-confirmed completed transaction) | Q5: Subject | R5: 1 | S5: [EXECUTED / HISTORICAL — price and rent undisclosed] Assignment of the 'long-term lease' and equipment; key money ASK $625,000 (Dec 2016) [10], later quoted $575,000 [13]; closing price, contract rent, remaining term and lease type never published. Implication: market participants paid a premium to occupy this space; contract rent below market at the time (inference). See key-money capitalization illustration below (ESTIMATE, not used in the market-rent calculation). | T5: https://www.27east.com/real-estate-news/marys-marvelous-in-amagansett-to-close-when-new-tenant-is-found-1404430 | https://behindthehedges.com/marys-marvelous-amagansett-shut-organic-krush-open/ | https://27east.com/east-hampton-press/marys-marvelous-leaves-amagansett-organic-krush-to-move-in-1633346
A6: 177 Main St — 2020 building sale | B6: 177 Main St | C6: Amagansett | D6: Restaurant building (fee sale, Indian Wells Tavern) | E6: 2900 | F6: n/a (sale) | G6: n/a — fee sale $2,825,000 | H6: =IF(ISNUMBER(G6),G6/12,"n/a") -> n/a | I6: =IFERROR(IF(ISNUMBER(G6),G6/E6,"n/a"),"n/a") -> n/a | J6: =IF(AND(LEFT(F6,3)="NNN",ISNUMBER(I6)),"Not stated; master "&TEXT('Executive Summary'!$B$8,"$0.00")&" applied","Unknown") -> Unknown | K6: =IF(AND(ISNUMBER(I6),LEFT(F6,3)="NNN"),I6+'Executive Summary'!$B$8,"n/a") -> n/a | L6: n/a | M6: Annual | N6: 2020 | O6: [81] | P6: C | Q6: Not a rent comp | R6: 1 | S6: [EXECUTED — SALE; NOT A RENT COMP] Building bought for $2.825M. SF ~2,900 per press (2,304 SF ground floor per Town ARB file [7]). | T6: https://www.danspapers.com/2020/02/highway-restaurant-buys-indian-wells-tavern
A7: Hampton Chutney renewal offer | B7: Amagansett Square | C7: Amagansett | D7: Food service (20-year legacy tenant) | E7: Unknown | F7: Unknown | G7: Not disclosed ('almost triple' prior rent) | H7: =IF(ISNUMBER(G7),G7/12,"n/a") -> n/a | I7: =IFERROR(IF(ISNUMBER(G7),G7/E7,"n/a"),"n/a") -> n/a | J7: =IF(AND(LEFT(F7,3)="NNN",ISNUMBER(I7)),"Not stated; master "&TEXT('Executive Summary'!$B$8,"$0.00")&" applied","Unknown") -> Unknown | K7: =IF(AND(ISNUMBER(I7),LEFT(F7,3)="NNN"),I7+'Executive Summary'!$B$8,"n/a") -> n/a | L7: Renewal (offer not accepted) | M7: Unknown | N7: Lease expired Oct 2020; offer spring 2021 | O7: [76][77][24] | P7: C | Q7: Qualitative | R7: 1 | S7: [HISTORICAL — qualitative executed-market event] Landlord's renewal offer at 'almost triple what we're paying now'. Space re-let to Doubles by July 2022; Hampton Chutney moved to 107 Newtown Lane, East Hampton, the former Mary's Marvelous store [77]. | T7: https://easthamptonstar.com/villages/2021527/hampton-chutney-co-squeezed-out-square | https://easthamptonstar.com/business-food/2021812/marvelous-new-home-hampton-chutney-co | https://www.easthamptonstar.com/villages-business/2023216/amagansett-main-street-flux
A8: Warby Parker, 48 Main St | B8: 48 Main St | C8: East Hampton Village | D8: Retail | E8: 1341 | F8: Not stated | G8: 167625 | H8: =IF(ISNUMBER(G8),G8/12,"n/a") -> 13968.75 | I8: =IFERROR(IF(ISNUMBER(G8),G8/E8,"n/a"),"n/a") -> 125 | J8: =IF(AND(LEFT(F8,3)="NNN",ISNUMBER(I8)),"Not stated; master "&TEXT('Executive Summary'!$B$8,"$0.00")&" applied","Unknown") -> Unknown | K8: =IF(AND(ISNUMBER(I8),LEFT(F8,3)="NNN"),I8+'Executive Summary'!$B$8,"n/a") -> n/a | L8: Unknown | M8: Annual | N8: Signed 2022-01-01 | O8: [55] | P8: D | Q8: Not scored | R8: 3 | S8: [EXECUTED (D) — may be an ask] Traded.co labels $125/SF ($167,625/yr) 'asking rent'. Trophy ceiling only; lease type not stated, so no effective rent. | T8: https://traded.co/deals/new-york/retail/lease/48-main-street/
A9: David Lewis Gallery, 53 The Circle | B9: 53 The Circle | C9: East Hampton Village | D9: Gallery | E9: 1645 | F9: Not stated | G9: 120085 | H9: =IF(ISNUMBER(G9),G9/12,"n/a") -> 10007.083 | I9: =IFERROR(IF(ISNUMBER(G9),G9/E9,"n/a"),"n/a") -> 73 | J9: =IF(AND(LEFT(F9,3)="NNN",ISNUMBER(I9)),"Not stated; master "&TEXT('Executive Summary'!$B$8,"$0.00")&" applied","Unknown") -> Unknown | K9: =IF(AND(ISNUMBER(I9),LEFT(F9,3)="NNN"),I9+'Executive Summary'!$B$8,"n/a") -> n/a | L9: Unknown | M9: Annual | N9: 2022-01-01 | O9: [54] | P9: D | Q9: Not scored | R9: 3 | S9: [EXECUTED (D) — labelled 'asking'] Village secondary data point ($73/SF). | T9: https://traded.co/deals/new-york/retail/lease/53-the-circle/
A10: 177 Main St — 2023 sale and Rowdy Hall lease | B10: 177 Main St | C10: Amagansett | D10: Restaurant building; leased to Rowdy Hall (opened Nov 2023) | E10: 2900 | F10: Unknown | G10: Lease rent not disclosed; sale $4,450,000 | H10: =IF(ISNUMBER(G10),G10/12,"n/a") -> n/a | I10: =IFERROR(IF(ISNUMBER(G10),G10/E10,"n/a"),"n/a") -> n/a | J10: =IF(AND(LEFT(F10,3)="NNN",ISNUMBER(I10)),"Not stated; master "&TEXT('Executive Summary'!$B$8,"$0.00")&" applied","Unknown") -> Unknown | K10: =IF(AND(ISNUMBER(I10),LEFT(F10,3)="NNN"),I10+'Executive Summary'!$B$8,"n/a") -> n/a | L10: Unknown | M10: Annual | N10: Sale 2023-01-17; lease 2023 | O10: [80][82][83][7] | P10: B/C | Q10: Not a rent comp | R10: 1 | S10: [EXECUTED — SALE + LEASE; rent undisclosed] Listed $4.995M (Oct 2022), sold $4.45M to ROP Amagansett LLC to lease out; ~58% above the 2020 price. See implied-yield illustration below — NOT A RENT COMP, carries no weight. | T10: https://behindthehedges.com/final-figure-amagansett-restaurant-sells-4-5m | https://www.danspapers.com/2022/10/amagansett-main-street-tavern-restaurant-building-for-sale | https://27east.com/east-hampton-press/rowdy-hall-to-move-from-east-hampton-village-to-amagansett-after-summer-2159344 | https://www.ehamptonny.gov/AgendaCenter/ViewFile/Item/2157?fileID=5624
A11: ='Comparable Properties'!A16 -> 53 The Circle (GreyVen) | B11: ='Comparable Properties'!B16 -> 53 The Circle | C11: ='Comparable Properties'!C16 -> East Hampton Village | D11: ='Comparable Properties'!D16 -> Luxury retail | E11: ='Comparable Properties'!E16 -> 1635 | F11: ='Comparable Properties'!F16 -> NNN | G11: ='Comparable Properties'!G16 -> 237075 | H11: ='Comparable Properties'!H16 -> 19756.25 | ... R11: ='Comparable Properties'!R16 -> 3 | S11: [EXECUTED per Traded.co, closed 2024-05-09; grade D] $145/SF NNN; corroborated by 6% cap on a $3,959,000 sale ask. Trophy-corridor ceiling; not a restaurant comparable. | T11: ='Comparable Properties'!T16 -> https://traded.co/deals/new-york/retail/lease/53-the-circle-1/
A12: ='Comparable Properties'!A12 -> 2095 Montauk Hwy restaurant | B12: ='Comparable Properties'!B12 -> 2095 Montauk Hwy | C12: ='Comparable Properties'!C12 -> Amagansett 11930 (Napeague, ~6 mi east of core) | D12: ='Comparable Properties'!D12 -> Restaurant, white box, 123 seats, double hood, 3BR apartment | E12: ='Comparable Properties'!E12 -> 4476 | F12: ='Comparable Properties'!F12 -> NNN | G12: ='Comparable Properties'!G12 -> 180000 | H12: ='Comparable Properties'!H12 -> 15000 | ... R12: ='Comparable Properties'!R12 -> 2 | S12: [CLOSED, broker-reported; Compass flags price 'Unverified'] $180,000 base + $40,000 NNN ($40.21 + $8.94/SF). The only closed Amagansett-ZIP food-service rent; low anchor. | T12: ='Comparable Properties'!T12 -> https://www.compass.com/homedetails/2095-Montauk-Hwy-Amagansett-NY-11930/1826297907410452777_lid/ | https://www.compass.com/agents/the-hamptons-commercial-real-estate-team/ | https://behindthehedges.com/fall-2024-food-market-commercial-real-estate
A13: Sea Dragon Books, 136 Main St | B13: 136 Main St | C13: Amagansett | D13: Bookstore (retail) | E13: Unknown | F13: Unknown | G13: Not disclosed | H13: =IF(ISNUMBER(G13),G13/12,"n/a") -> n/a | I13: =IFERROR(IF(ISNUMBER(G13),G13/E13,"n/a"),"n/a") -> n/a | J13: =IF(AND(LEFT(F13,3)="NNN",ISNUMBER(I13)),"Not stated; master "&TEXT('Executive Summary'!$B$8,"$0.00")&" applied","Unknown") -> Unknown | K13: =IF(AND(ISNUMBER(I13),LEFT(F13,3)="NNN"),I13+'Executive Summary'!$B$8,"n/a") -> n/a | L13: Two-year lease | M13: Unknown | N13: 2026 | O13: [86] | P13: C | Q13: Not scored | R13: 2 | S13: [EXECUTED — rent undisclosed] Confirms leasing activity on the Main Street frontage. | T13: https://easthamptonstar.com/villages-business/202672/amagansetts-west-end-sees-business-boom
A15: ILLUSTRATION (ESTIMATE): 2016–17 key money capitalized as an annual rent differential — loose upper bound, NOT used in the market-rent calculation
A16: Discount rate (assumed) | B16: 0.1 | C16: Assumed 10% rate from the executed-transactions research; remaining terms are assumptions.
A17: Key money (ASK) | B17: Amount | C17: Source | D17: 10-yr: annual | E17: 10-yr: monthly | F17: 15-yr: annual | G17: 15-yr: monthly | H17: 20-yr: annual | I17: 20-yr: monthly
A18: Remaining term (years) | D18: 10 | F18: 15 | H18: 20
A19: Later quote | B19: 575000 | C19: [13] | D19: =PMT($B$16,D$18,-$B19) -> 93578.602 | E19: =D19/12 -> 7798.2168 | F19: =PMT($B$16,F$18,-$B19) -> 75597.422 | G19: =F19/12 -> 6299.7851 | H19: =PMT($B$16,H$18,-$B19) -> 67539.284 | I19: =H19/12 -> 5628.2737
A20: Original ask | B20: 625000 | C20: [10] | D20: =PMT($B$16,D$18,-$B20) -> 101715.87 | E20: =D20/12 -> 8476.3227 | F20: =PMT($B$16,F$18,-$B20) -> 82171.111 | G20: =F20/12 -> 6847.5925 | H20: =PMT($B$16,H$18,-$B20) -> 73412.265 | I20: =H20/12 -> 6117.6888
A21: Report check: $575,000 → $93,579 / $75,597 / $67,539 per year; $625,000 → $101,716 / $82,171 / $73,412. Part of the payment bought used equipment, goodwill and the scarce wet-use status, so the figures are directional only: in 2016–17 informed buyers valued this leasehold above its contract rent.
A23: 177 MAIN STREET IMPLIED-YIELD ILLUSTRATION — ESTIMATE ONLY, NOT A RENT COMP (carries no weight in the calculation)
A24: 2023 sale price ($) | B24: 4450000 | C24: [80]
A25: 2020 sale price ($) | B25: 2825000 | C25: [81]
A26: Investor yield, low (assumed, unsourced) | B26: 0.055 | C26: Assumption
A27: Investor yield, high (assumed, unsourced) | B27: 0.065 | C27: Assumption
A28: Building SF per press coverage | B28: 2900 | C28: Press coverage
A29: Ground-floor SF per Town ARB file | B29: 2304 | C29: [7] (also 650 SF lower level, 94 seats)
A31: Output (ESTIMATE) | B31: Low yield | C31: High yield
A32: Implied net income ($/yr) | B32: =$B$24*$B$26 -> 244750 | C32: =$B$24*$B$27 -> 289250
A33: Implied $/SF on ~2,900 SF | B33: =B32/$B$28 -> 84.396552 | C33: =C32/$B$28 -> 99.741379
A34: Implied $/SF on 2,304 SF ground floor | B34: =B32/$B$29 -> 106.2283 | C34: =C32/$B$29 -> 125.54253
A35: Price change 2020 → 2023 | B35: =$B$24/$B$25-1 -> 0.57522124
A36: Report check: $244,750–$289,250/yr; $84–$100/SF on ~2,900 SF; about $106–$126/SF on 2,304 SF; price up about 58%. Inferred from a sale price, not a lease; the buyer may have priced in land value or upside.
A38: NOTES & SOURCES
A39: Asking vs executed: most figures in this workbook are ASKING rents on listings, not executed leases. No executed Amagansett commercial rent is publicly disclosed for 2014–2026. The only closed Amagansett-ZIP food-service lease (2095 Montauk Hwy, closed 2025-06-08) is broker-reported and Compass flags its price 'Unverified' [42]. Asks are converted to an achieved basis with a moderate 5–10% discount (asks on market >180 days without a cut −10%; other asks −5%; closed 0%). Trophy village rows ($145–$240/SF) are excluded from the conclusion except as an outer ceiling.
A40: NNN assumption ($7.00/SF, range $5.00–$8.75; master input on Executive Summary): real estate taxes from broker-published tax bills run $1.38–$3.22/SF on small village commercial buildings [68][69][70][71]; the subject's own taxes are about $2.96/SF [3]; taxes alone at 74A are $4.92/SF [31]; the one stated all-in Amagansett NNN figure is $8.94/SF at 2095 Montauk Highway [42]; taxes at 136 Main / 11 Indian Wells run about $1.31–$2.02/SF [36]; and a generic national benchmark puts retail NNN at $4–$8/SF [72]. Insurance and maintenance components (about $1.00–$2.50 and $1.00–$3.00/SF respectively) are unsourced assumptions and should be replaced with the subject's actual figures.
A41: Labels: ASK = asking rent on a listing; EXECUTED/CLOSED = signed, assigned or broker-reported closed lease; HISTORICAL = dated past listing or event; BROKER OPINION = broker's quoted range; ESTIMATE = figure inferred or calculated in the report. Grades: A = government record or recorded transaction; B = broker listing with detailed terms or established real estate publication; C = historical listing, local newspaper or business website; D = aggregator, unverified database or search snippet.
A42: Source: '207 Main Street, Amagansett — Commercial Market Rent Assessment', effective 2026-10-07 (research/reports/207 Main Street Amagansett market rent.md). Bracketed numbers refer to the Sources tab, which lists every URL (all accessed 2026-10-07).

Sheet Historical Listings
A1: Historical Listings — dated time series, 1997–2026
A2: From the report's Historical Market Evidence section (plus its Montauk notes and the subject's own 2016–2017 listing history). Ordered by date. No archived listing captures exist (Wayback CDX blocked; LoopNet/Crexi 403).
A3: Label for each event is shown in brackets at the start of Event / Listing. Green cells link to the Comparable Properties or Executed Transactions tabs.
A4: Property | B4: Address | C4: Hamlet | D4: Date | E4: Event / Listing | F4: Asking Rent | G4: $/SF | H4: Seasonal / Annual | I4: Outcome | J4: Source | K4: Grade | L4: Source URL
A5: East Hampton Village retail (trend line) | B5: Village core (Main St / Newtown Ln) | C5: East Hampton Village | D5: 1997-05 | E5: [BROKER OPINION] Village retail $45–$70/SF; spaces under 1,000 SF 'proportionately more' | F5: n/a (broker range) | G5: $45–$70 | H5: Annual | I5: Market commentary | J5: [87] | K5: C | L5: https://www.easthamptonstar.com/archive/village-going-going
A6: East Hampton Village prime (trend line) | B6: Prime village blocks | C6: East Hampton Village | D6: 2007–08 | E6: [BROKER OPINION] Prime village retail 'up to $250 a foot' | F6: n/a (broker range) | G6: up to $250 | H6: Annual | I6: Pre-crisis peak | J6: [88] | K6: B | L6: https://therealdeal.com/magazine/new-york-june-2009/retail-cools-in-hamptons
A7: East Hampton Village; Montauk (trend line) | B7: Village core; Montauk | C7: East Hampton Village / Montauk | D7: 2009-06 | E7: [BROKER OPINION] $175–$200/SF asks; achieved 20–25% below unchanged asks; Montauk landlords 'giving 20 to 30 percent off' | F7: n/a (broker range) | G7: $175–$200 (ask) | H7: Annual | I7: Achieved 20–25% below asks (EH); 20–30% off (Montauk) | J7: [88] | K7: B | L7: https://therealdeal.com/magazine/new-york-june-2009/retail-cools-in-hamptons
A8: East Hampton / Southampton / Bridgehampton–Sag Harbor (trend line) | B8: Village cores | C8: East Hampton; Southampton; Bridgehampton; Sag Harbor | D8: 2011 | E8: [BROKER OPINION] Multiyear leases $110–$140 (EH), $70–$75 (Southampton), about $50 (Bridgehampton, Sag Harbor) | F8: n/a (broker range) | G8: $110–$140 (EH); $70–$75 (SH); ~$50 (BH/SgH) | H8: Annual | I8: Post-crisis trough; 'prime shopping season is just three months' | J8: [89] | K8: B | L8: https://www.corcoran.com/nyc/press-mention/display/12619
A9: Outdoors store | B9: Main St | C9: Amagansett | D9: 2012-04 | E9: [HISTORICAL] 15-year lease not renewed | F9: Undisclosed | G9: n/a | H9: Annual | I9: Space later split between two tenants | J9: [125][74] | K9: C | L9: https://www.easthamptonstar.com/archive/outdoors-heading-out | https://www.easthamptonstar.com/archive/square-dance-amagansett
A10: Gone Local | B10: Main St | C10: Amagansett | D10: 2013-05 | E10: [HISTORICAL] Month-to-month tenant evicted; owner could afford 'as much as $5,000 per month' for a new space | F10: Tenant budget ≤ $5,000/mo (not a rent) | G10: n/a | H10: Month-to-month | I10: Tenant relocated | J10: [73] | K10: C | L10: https://patch.com/new-york/easthampton/gone-local-goes-looking-for-a-new-space
A11: Amagansett Square | B11: Amagansett Square, Main St | C11: Amagansett | D11: 2015–16 | E11: [HISTORICAL] Four vacancies in late 2015 | F11: n/a | G11: n/a | H11: Annual | I11: Square 'filled to capacity' by May 2016 | J11: [74][75] | K11: C | L11: https://www.easthamptonstar.com/archive/square-dance-amagansett | https://www.easthamptonstar.com/archive/lifestyle-shops-fill-gansett-square-capacity
A12: East Hampton Village / Southampton (trend line) | B12: Village cores | C12: East Hampton Village; Southampton | D12: 2016-02 | E12: [BROKER OPINION] Average $125/SF (EH); $90/SF (Southampton) | F12: n/a (broker average) | G12: $125 (EH); $90 (SH) | H12: Annual | I12: Market commentary | J12: [90] | K12: C | L12: https://www.27east.com/real-estate-news/pulse-points-1407695
A13: 2510 Montauk Hwy corner building | B13: 2510 Montauk Hwy | C13: Bridgehampton | D13: 2016-12 | E13: [ASK] Main floor $70/SF plus taxes and CAM | F13: n/a | G13: 70 | H13: Annual | I13: Outcome unknown | J13: [99] | K13: C | L13: https://www.easthamptonstar.com/archive/corner-building-1075-million
A14: 207 Main St — SUBJECT (Mary's Marvelous leasehold) | B14: 207 Main St | C14: Amagansett | D14: 2016-12-08 | E14: [HISTORICAL ASK] Douglas Elliman markets 'key money' for the business, long-term lease and equipment; contract rent not published | F14: Key money ASK $625,000 (rent undisclosed) | G14: n/a | H14: Annual | I14: 'Several serious inquiries' within a day | J14: [9][10][12] | K14: B | L14: https://patch.com/new-york/riverhead/marys-marvelous-amagansett-close-new-tenant-sought | https://www.27east.com/real-estate-news/marys-marvelous-in-amagansett-to-close-when-new-tenant-is-found-1404430 | https://behindthehedges.com/marys-marvelous-in-amagansett-closing-and-available-to-lease/
A15: 716 Montauk Hwy retail plaza | B15: 716 Montauk Hwy | C15: Montauk | D15: 2016 → 2017-03 | E15: [HISTORICAL — SALE ASK] Sale price cut from $8.9M (2016) to $6.7M (March 2017) | F15: n/a (sale ask) | G15: n/a | H15: n/a | I15: Montauk cyclical discounting | J15: [97] | K15: B | L15: https://behindthehedges.com/montauk-retail-plaza-cheaper
A16: 207 Main St — SUBJECT (lease assignment) | B16: 207 Main St | C16: Amagansett | D16: 2017-06-12 | E16: [EXECUTED] Assignment to Organic Krush closed Monday, June 12, 2017; price not disclosed | F16: Undisclosed | G16: n/a | H16: Annual | I16: Organic Krush opened June 2017 | J16: [15] | K16: B | L16: https://27east.com/east-hampton-press/marys-marvelous-leaves-amagansett-organic-krush-to-move-in-1633346
A17: 207 Main St — SUBJECT (reported price) | B17: 207 Main St | C17: Amagansett | D17: 2017-06-15 | E17: [HISTORICAL] Behind the Hedges: 'the lease, listed for $575K, has sold' (27east cites only $625,000) | F17: Key money quoted $575,000 (rent undisclosed) | G17: n/a | H17: Annual | I17: Leasehold assigned ($625K → $575K key money) | J17: [13][14] | K17: B/C | L17: https://behindthehedges.com/marys-marvelous-amagansett-shut-organic-krush-open/ | https://www.danspapers.com/2017/06/behind-the-hedges-organic-krush-in-amagansett
A18: Southampton (trend line) | B18: Main St; Jobs Ln | C18: Southampton Village | D18: 2017-07 | E18: [BROKER OPINION] Main St $140–$150; Jobs Lane $100–$110; pop-ups (4–6 months) at 'two-thirds to three-fourths of the annual asking rent' | F18: n/a (broker range) | G18: $140–$150 (Main); $100–$110 (Jobs) | H18: Annual; pop-ups seasonal | I18: Basis of the 0.67–0.75 seasonal factor | J18: [91] | K18: B | L18: https://therealdeal.com/magazine/new-york-july-2017/fashion-and-furnishings-lead-a-retail-revival-in-southampton/
A19: 74A Montauk Hwy (Coche Comedor) | B19: 74A Montauk Hwy | C19: Amagansett | D19: 2019-05 | E19: [HISTORICAL] Honest Man opened Coche Comedor; 'The company already owned the space' | F19: n/a | G19: n/a | H19: Annual | I19: Owner-occupied | J19: [79] | K19: B | L19: https://therealdeal.com/tristate/issues_articles/the-hamptons-new-hotspots
A20: Southampton / Amagansett (trend line) | B20: Village cores | C20: Southampton; Amagansett | D20: 2019-06 | E20: [BROKER OPINION] Southampton asks fell from ~$110 to $85 (Main) and $50 (Jobs Lane); 'Sag Harbor, Amagansett and Bridgehampton saw little turnover' | F20: Entry-level pop-ups $75,000–$100,000/season | G20: $85 (Main); $50 (Jobs) | H20: Annual; pop-ups seasonal | I20: Amagansett: little turnover | J20: [92] | K20: B | L20: https://therealdeal.com/new-york/tristate/2019/06/03/revolving-retail-in-the-hamptons/
A21: 177 Main St (Indian Wells Tavern) | B21: 177 Main St | C21: Amagansett | D21: 2020 | E21: [EXECUTED — SALE] Building bought for $2.825M | F21: n/a (sale) | G21: n/a | H21: n/a | I21: Re-sold 2023 for $4.45M | J21: [81] | K21: C | L21: https://www.danspapers.com/2020/02/highway-restaurant-buys-indian-wells-tavern
A22: Martell's / Montauk Fuels | B22: Montauk | C22: Montauk | D22: 2016 → 2021 | E22: [HISTORICAL — SALE ASK] Sale-ask series from $10.5M (2016) to $5.475M (2021) | F22: n/a (sale ask) | G22: n/a | H22: n/a | I22: Montauk cyclical discounting | J22: [127] | K22: B | L22: https://behindthehedges.com/two-commercial-properties-in-montauk-back-on-the-market/
A23: 249 Main St, Building B pop-up | B23: 249 Main St | C23: Amagansett | D23: 2021 | E23: [HISTORICAL ASK] Seasonal pop-up '50K' for May 1–Sept 2021 (basis ambiguous) | F23: ='Comparable Properties'!B46 -> 50000 | G23: =TEXT('Comparable Properties'!F46,"$0")&"–"&TEXT('Comparable Properties'!G46,"$0")&" per season" -> $25–$50 per season | H23: Seasonal | I23: Outcome unknown | J23: [47] | K23: C | L23: https://www.corcoran.com/listing/for-rent/249-main-street-amagansett-ny-11930/5981523/regionId/3
A24: Hampton Chutney (Amagansett Square) | B24: Amagansett Square | C24: Amagansett | D24: 2021-05 | E24: [HISTORICAL — OFFER] Renewal offered at 'almost triple' the prior rent | F24: Not disclosed (~3x prior) | G24: n/a | H24: Annual | I24: Not accepted; Doubles opened in the space July 2022 | J24: [76][77][24] | K24: C | L24: https://easthamptonstar.com/villages/2021527/hampton-chutney-co-squeezed-out-square | https://easthamptonstar.com/business-food/2021812/marvelous-new-home-hampton-chutney-co | https://www.easthamptonstar.com/villages-business/2023216/amagansett-main-street-flux
A25: East Hampton Village Main / Newtown (trend line) | B25: Main St; Newtown Ln | C25: East Hampton Village | D25: 2021-09 | E25: [BROKER OPINION] Average $125–$150/SF | F25: n/a (broker average) | G25: $125–$150 | H25: Annual | I25: Post-COVID recovery | J25: [93] | K25: C | L25: https://www.easthamptonstar.com/villages/202192/general-store-east-hampton-its-challenge
A26: 136 Main St; 11 Indian Wells Hwy | B26: 136 Main St; 11 Indian Wells Hwy | C26: Amagansett | D26: 2021-11 / 2022-12 | E26: [EXECUTED — SALES] Sold for $5.6M and $5.2M to the same group | F26: n/a (sales) | G26: n/a | H26: n/a | I26: Assemblage offered for sale at $19M in 2026 | J26: [85][84] | K26: C/B | L26: https://www.easthamptonstar.com/business/2022317/recorded-deeds-031722 | https://behindthehedges.com/amagansett-applied-arts-building-sells-5-2-m
A27: East Hampton Village retail leases (trend line) | B27: 53 The Circle; 48 Main St | C27: East Hampton Village | D27: 2022–24 | E27: [EXECUTED (D)] Retail leases at $73, $125 and $145/SF (David Lewis 2022, Warby Parker 2022, GreyVen 2024) | F27: See Executed Transactions | G27: =TEXT('Executed Transactions'!I9,"$0")&" / "&TEXT('Executed Transactions'!I8,"$0")&" / "&TEXT('Executed Transactions'!I11,"$0") -> $73 / $125 / $145 | H27: Annual | I27: Trophy ceiling only | J27: [53][54][55] | K27: D | L27: https://traded.co/deals/new-york/retail/lease/53-the-circle-1/ | https://traded.co/deals/new-york/retail/lease/53-the-circle/ | https://traded.co/deals/new-york/retail/lease/48-main-street/
A28: East End retail (trend line) | B28: East End | C28: East End | D28: 2022-11 | E28: [BROKER OPINION — market data] About $46/SF; +9.8% over 12 months; +62.2% vs a decade earlier (likely CoStar-sourced) | F28: n/a (market average) | G28: 46 | H28: Annual | I28: Basis of the +10% market-timing adjustment | J28: [94] | K28: B | L28: https://behindthehedges.com/southampton-restaurant-sale-first-time-20/
A29: 177 Main St | B29: 177 Main St | C29: Amagansett | D29: 2023-01-17 | E29: [EXECUTED — SALE] Sold for $4.45M to ROP Amagansett LLC (listed $4.995M Oct 2022) | F29: n/a (sale) | G29: n/a | H29: n/a | I29: Leased to Rowdy Hall (opened Nov 2023); rent undisclosed | J29: [80][82][83] | K29: B/C | L29: https://behindthehedges.com/final-figure-amagansett-restaurant-sells-4-5m | https://www.danspapers.com/2022/10/amagansett-main-street-tavern-restaurant-building-for-sale | https://27east.com/east-hampton-press/rowdy-hall-to-move-from-east-hampton-village-to-amagansett-after-summer-2159344
A30: Newtown Lane | B30: Newtown Ln | C30: East Hampton Village | D30: 2023-04 | E30: [BROKER OPINION] 'over 14 offers... the price was $250 per square foot' (rent or price ambiguous) | F30: n/a | G30: $250 (ambiguous) | H30: n/a | I30: Ambiguous | J30: [95] | K30: B | L30: https://behindthehedges.com/hamptons-commercial-real-estate-market/
A31: 519–521 Montauk Hwy | B31: 519–521 Montauk Hwy | C31: Amagansett | D31: 2023-06 | E31: [HISTORICAL] Listed for sale at $7.95M; vacant 'for the last few years'; earlier 7-Eleven lease abandoned | F31: n/a (sale ask) | G31: n/a | H31: n/a | I31: Lease status unverified in 2026 | J31: [45] | K31: B | L31: https://behindthehedges.com/amagansett-commercial-property-lists-8-million
A32: 2095 Montauk Hwy restaurant | B32: 2095 Montauk Hwy | C32: Amagansett (Napeague) | D32: 2024-10 | E32: [ASK] $180,000/year base for 4,476 SF | F32: ='Comparable Properties'!G12 -> 180000 | G32: ='Comparable Properties'!I12 -> 40.214477 | H32: Annual | I32: Rented June 2025 at the same figure | J32: [43] | K32: B | L32: https://behindthehedges.com/fall-2024-food-market-commercial-real-estate
A33: 2095 Montauk Hwy restaurant | B33: 2095 Montauk Hwy | C33: Amagansett (Napeague) | D33: 2025-06-08 | E33: [CLOSED] Rented; $180,000 base + $40,000 NNN (Compass flags price 'Unverified') | F33: ='Comparable Properties'!G12 -> 180000 | G33: ='Comparable Properties'!I12 -> 40.214477 | H33: Annual | I33: Only closed Amagansett-ZIP food-service lease | J33: [42] | K33: B | L33: https://www.compass.com/homedetails/2095-Montauk-Hwy-Amagansett-NY-11930/1826297907410452777_lid/
A34: 716 Montauk Hwy retail building | B34: 716 Montauk Hwy | C34: Montauk | D34: 2025-09 | E34: [ASK] 1,450 SF units at $9,750/month (about $80.69/SF if per unit; basis ambiguous) | F34: $9,750/month per unit | G34: 80.69 | H34: Annual | I34: Outcome unknown | J34: [96] | K34: B | L34: https://behindthehedges.com/premier-retail-building-downtown-montauk-10m/
A35: 74A Montauk Hwy (Coche Comedor) | B35: 74A Montauk Hwy | C35: Amagansett | D35: 2025-09-27 | E35: [HISTORICAL] Coche Comedor closed after six years | F35: n/a | G35: n/a | H35: Annual | I35: Space offered for lease in 2026 | J35: [78] | K35: C | L35: https://www.easthamptonstar.com/food/2025925/adios-coche-comedor
A36: 74A Montauk Hwy (former Coche Comedor) | B36: 74A Montauk Hwy | C36: Amagansett | D36: 2026 | E36: [ASK] $240,000 NNN + $700,000 key money; $175,000 seasonal option | F36: ='Comparable Properties'!G5 -> 240000 | G36: ='Comparable Properties'!I5 -> 84.805654 | H36: Annual (seasonal option also offered) | I36: ~194 days on market, no price cut | J36: [28] | K36: B | L36: https://hamptonscommercialre.com/properties/iconic-amagansett-restaurant-turn-key-opportunity/
A37: 11 Indian Wells Hwy (three floors) | B37: 11 Indian Wells Hwy | C37: Amagansett | D37: 2026 | E37: [ASK] Ground level / second floor / first floor, NNN | F37: See Comparable Properties | G37: =TEXT('Comparable Properties'!I8,"$0")&" / "&TEXT('Comparable Properties'!I9,"$0")&" / "&TEXT('Comparable Properties'!I7,"$0") -> $35 / $50 / $65 | H37: Annual | I37: ~316–547 days on market, no cut | J37: [33][34][35] | K37: B | L37: https://hamptonscommercialre.com/properties/first-floor-commercial-space/ | https://hamptonscommercialre.com/properties/ground-level-commercial-offering/ | https://hamptonscommercialre.com/properties/second-floor-amagansett-commercial-flex-space-iconic-building/
A38: 136 Main St, Unit 1; 136 Main + 11 Indian Wells assemblage | B38: 136 Main St | C38: Amagansett | D38: 2026 | E38: [ASK] Unit 1 $192 NNN (withdrawn); assemblage for sale at $19M | F38: ='Comparable Properties'!G10 -> 96000 | G38: ='Comparable Properties'!I10 -> 192 | H38: Annual | I38: Broker page 404 on 2026-10-07 (likely leased or withdrawn) | J38: [38][36] | K38: D/B | L38: https://www.loopnet.com/Listing/136-Main-St-Amagansett-NY/32986784/ | https://hamptonscommercialre.com/properties/premier-amagansett-commercial-assemblage-136-main-street-11-indian-wells-hwy-amagansett/
A39: Amagansett west end | B39: 136 Main St frontage | C39: Amagansett | D39: 2026-07-02 | E39: [HISTORICAL] 'Business boom'; new tenants at 136 Main St (Sett Coffee, Sea Dragon Books, Jamagansett, LaParlour) | F39: n/a | G39: n/a | H39: Annual | I39: Frontage filled in 2026 | J39: [86] | K39: C | L39: https://easthamptonstar.com/villages-business/202672/amagansetts-west-end-sees-business-boom
A41: What the history shows (report): Hamptons retail rents are cyclical (EH Village asks fell from about $250 to $110–$140 between 2008 and 2011, then recovered); the post-2020 period is a step-up (an Amagansett renewal offer at about 3x in 2021, East End rents +9.8% in a year to Nov 2022, an Amagansett restaurant building up about 58% in under three years); Amagansett vacated spaces have re-let within about a season; and seasonality is priced explicitly (a season ≈ two-thirds to three-quarters of a year's rent). A lease negotiated in 2002 or assigned in 2017 predates the post-2020 step-up.
A43: NOTES & SOURCES
A44: Asking vs executed: most figures in this workbook are ASKING rents on listings, not executed leases. No executed Amagansett commercial rent is publicly disclosed for 2014–2026. The only closed Amagansett-ZIP food-service lease (2095 Montauk Hwy, closed 2025-06-08) is broker-reported and Compass flags its price 'Unverified' [42]. Asks are converted to an achieved basis with a moderate 5–10% discount (asks on market >180 days without a cut −10%; other asks −5%; closed 0%). Trophy village rows ($145–$240/SF) are excluded from the conclusion except as an outer ceiling.
A45: NNN assumption ($7.00/SF, range $5.00–$8.75; master input on Executive Summary): real estate taxes from broker-published tax bills run $1.38–$3.22/SF on small village commercial buildings [68][69][70][71]; the subject's own taxes are about $2.96/SF [3]; taxes alone at 74A are $4.92/SF [31]; the one stated all-in Amagansett NNN figure is $8.94/SF at 2095 Montauk Highway [42]; taxes at 136 Main / 11 Indian Wells run about $1.31–$2.02/SF [36]; and a generic national benchmark puts retail NNN at $4–$8/SF [72]. Insurance and maintenance components (about $1.00–$2.50 and $1.00–$3.00/SF respectively) are unsourced assumptions and should be replaced with the subject's actual figures.
A46: Labels: ASK = asking rent on a listing; EXECUTED/CLOSED = signed, assigned or broker-reported closed lease; HISTORICAL = dated past listing or event; BROKER OPINION = broker's quoted range; ESTIMATE = figure inferred or calculated in the report. Grades: A = government record or recorded transaction; B = broker listing with detailed terms or established real estate publication; C = historical listing, local newspaper or business website; D = aggregator, unverified database or search snippet.
A47: Source: '207 Main Street, Amagansett — Commercial Market Rent Assessment', effective 2026-10-07 (research/reports/207 Main Street Amagansett market rent.md). Bracketed numbers refer to the Sources tab, which lists every URL (all accessed 2026-10-07).

Sheet Adjustments
A1: Adjustments — seven strongest comparables
A2: Sign convention: + means the subject is superior on that factor (comparable adjusted up); − means the comparable is superior (adjusted down). Normalization (transaction status, market timing) is applied multiplicatively; property adjustments are summed and applied to the normalized rent.
A3: Adjusted $/SF = Normalized $/SF × (1 + Net property adjustment). Percentages stored as fractions. Blue = report inputs; size adjustment and normalized/adjusted values are formulas.
A5: Factor | B5: 74A Montauk Hwy | C5: 11 Indian Wells, 1st fl. | D5: 2095 Montauk Hwy | E5: 17 S Edison, Montauk | F5: 249 Main St (2021) | G5: 9 Railroad Ave, EH | H5: 7 Hill St, Southampton | I5: Rationale (one line per adjustment)
A6: Comparable (Comparable Properties row) | B6: ='Comparable Properties'!A5 -> Former Coche Comedor (annual option) | C6: ='Comparable Properties'!A7 -> 11 Indian Wells Hwy, first floor | D6: ='Comparable Properties'!A12 -> 2095 Montauk Hwy restaurant | E6: ='Comparable Properties'!A15 -> 17 S Edison St restaurant | F6: ='Comparable Properties'!A14 -> 249 Main St, Building B pop-up | G6: ='Comparable Properties'!A19 -> 9 Railroad Ave | H6: ='Comparable Properties'!A25 -> 7 Hill St (inline) | I6: Linked from Comparable Properties.
A7: Evidence label | B7: ASK | C7: ASK | D7: CLOSED | E7: ASK | F7: HISTORICAL ASK | G7: ASK | H7: ASK
A8: SF (Comparable Properties) | B8: ='Comparable Properties'!E5 -> 2830 | C8: ='Comparable Properties'!E7 -> 2480 | D8: ='Comparable Properties'!E12 -> 4476 | E8: ='Comparable Properties'!E15 -> 2729 | F8: ='Comparable Properties'!E14 -> 2000 | G8: ='Comparable Properties'!E19 -> 3000 | H8: ='Comparable Properties'!E25 -> 925
A9: SF used for size adjustment | B9: =B8 -> 2830 | C9: =C8 -> 2480 | D9: =D8 -> 4476 | E9: =E8 -> 2729 | F9: =$C$47 -> 1000 | G9: =G8 -> 3000 | H9: =H8 -> 925 | I9: 249 Main: 1,000 SF ground floor (report Size note); others = full SF.
A10: Starting rent as reported ($/SF NNN; 249 Main = $ per season) | B10: ='Comparable Properties'!I5 -> 84.805654 | C10: ='Comparable Properties'!I7 -> 65 | D10: ='Comparable Properties'!I12 -> 40.214477 | E10: ='Comparable Properties'!I15 -> 57.163796 | F10: ='Comparable Properties'!B46 -> 50000 | G10: ='Comparable Properties'!I19 -> 83.333333 | H10: ='Comparable Properties'!I25 -> 71.351351
A11: Unadjusted $/SF (annual NNN basis) | B11: =B10 -> 84.805654 | C11: =C10 -> 65 | D11: =D10 -> 40.214477 | E11: =E10 -> 57.163796 | F11: =F10/'Comparable Properties'!$C$34/(($C$47)+($C$48)*($C$49))-'Executive Summary'!$B$8 -> 39.948357 | G11: =G10 -> 83.333333 | H11: =H10 -> 71.351351 | I11: 249 Main: $50,000 ÷ 0.71 = $70,423 annual-equiv.; ÷ 1,500 SF ground-equiv. (basement at 50%) = $46.95 gross-equiv.; less NNN $7.00 = $39.95 NNN.
A12: Transaction status (ask → achieved) | B12: -0.1 | C12: -0.1 | D12: 0 | E12: -0.05 | F12: -0.05 | G12: -0.1 | H12: -0.05 | I12: Asks >180 days without a cut −10% (74A, 11 IW, 9 Railroad); other asks −5%; closed 0% [88][100][101].
A13: Market timing | B13: 0 | C13: 0 | D13: 0 | E13: 0 | F13: 0.1 | G13: 0 | H13: 0 | I13: 2021 figure +10% to 2026 (East End +9.8% in a year to Nov 2022 [94]; LI asks ~+9% YoY in 2026 [113]); 2025–26 figures not time-adjusted.
A14: Normalized $/SF | B14: =B11*(1+B12)*(1+B13) -> 76.325088 | C14: =C11*(1+C12)*(1+C13) -> 58.5 | D14: =D11*(1+D12)*(1+D13) -> 40.214477 | E14: =E11*(1+E12)*(1+E13) -> 54.305606 | F14: =F11*(1+F12)*(1+F13) -> 41.746033 | G14: =G11*(1+G12)*(1+G13) -> 75 | H14: =H11*(1+H12)*(1+H13) -> 67.783784 | I14: Unadjusted × (1 + transaction status) × (1 + market timing).
A15: PROPERTY ADJUSTMENTS (summed)
A16: Location / visibility / Main St frontage | B16: 0 | C16: 0.05 | D16: 0.15 | E16: 0 | F16: 0 | G16: -0.05 | H16: -0.05 | I16: Subject is an at-grade corner storefront in the Main St core [2][4][18]; 11 IW entered by stair (+5%); 2095 off-core Napeague (+15%, conservative vs 35–65% village-tier spreads [89]); EH and Southampton villages have larger trade areas (−5%).
A17: Size | B17: =ROUND((B9/'Executive Summary'!$B$6)^$C$45-1,2) -> 0.15 | C17: =ROUND((C9/'Executive Summary'!$B$6)^$C$45-1,2) -> 0.13 | D17: =ROUND((D9/'Executive Summary'!$B$6)^$C$45-1,2) -> 0.23 | E17: =ROUND((E9/'Executive Summary'!$B$6)^$C$45-1,2) -> 0.15 | F17: =ROUND((F9/'Executive Summary'!$B$6)^$C$45-1,2) -> -0.01 | G17: =ROUND((G9/'Executive Summary'!$B$6)^$C$45-1,2) -> 0.16 | H17: =ROUND((H9/'Executive Summary'!$B$6)^$C$45-1,2) -> -0.03 | I17: (Comparable SF ÷ subject SF)^0.15 − 1, rounded to whole %; smaller spaces command higher $/SF [87][63]; 249 Main uses its 1,000 SF ground floor.
A18: Condition (building condition / historic) | B18: -0.05 | C18: -0.05 | D18: 0 | E18: 0 | F18: 0 | G18: -0.05 | H18: -0.05 | I18: Renovated / built-out comparables −5% against a subject with a repair history and Unknown current condition [18][28][33][57][65]; no adjustment for ARB constraints alone.
A19: Restaurant infrastructure (kitchen / readiness) | B19: -0.1 | C19: 0.1 | D19: 0 | E19: -0.1 | F19: 0.1 | G19: 0.1 | H19: 0.05 | I19: Large kitchens −10% (74A, 17 S Edison) vs subject's tiny kitchen [18]; dry spaces +10% for subject's scarce wet use [10][12]; 7 Hill 'modified wet uses' +5%; 2095 double hoods offset white box (0).
A20: Outdoor space (patio) | B20: -0.05 | C20: 0 | D20: -0.05 | E20: 0 | F20: 0.05 | G20: 0.05 | H20: 0.05 | I20: 74A expansive patio / 30 outdoor seats and 2095's 450 SF outdoor seating −5% [28][42]; no stated outdoor space +5% (subject has a patio [9]).
A21: Parking | B21: -0.1 | C21: -0.05 | D21: -0.1 | E21: 0.05 | F21: 0 | G21: -0.1 | H21: 0 | I21: On-site parking superior: 74A (31 spaces), 2095, 9 Railroad −10%; 11 IW shared 33-space lot −5%; 17 S Edison alley only +5% (subject adjoins ~185-space Town lot [25]).
A22: Lease structure | B22: 0 | C22: 0 | D22: 0 | E22: 0 | F22: 0 | G22: 0 | H22: 0 | I22: All compared on NNN base rent; 249 Main's pop-up figure converted in normalization (0).
A23: Seasonality | B23: 0 | C23: 0 | D23: 0.05 | E23: 0 | F23: 0 | G23: -0.05 | H23: -0.05 | I23: Hamlet market, not tenant hours: Napeague stretch resort-dependent (+5%); year-round EH / Southampton village populations (−5%) [89].
A24: Foot traffic | B24: 0.05 | C24: 0 | D24: 0.05 | E24: -0.05 | F24: 0 | G24: 0.05 | H24: 0 | I24: Subject's pedestrian position +5% vs 74A, 2095's drive-to stretch and Railroad Ave's secondary street; downtown Montauk stronger summer volume −5% [50].
A25: Signage / zoning | B25: 0 | C25: 0 | D25: 0 | E25: 0 | F25: 0 | G25: 0 | H25: 0 | I25: All seven permit the comparable's current use; subject's ARB sign limits offset by core position (0).
A26: Storage / ancillary space | B26: -0.05 | C26: 0 | D26: -0.1 | E26: 0 | F26: 0 | G26: 0 | H26: 0 | I26: 74A finished lower level, legal prep area and office −5%; 2095 three-bedroom apartment and 1.1 acres −10% [28][42].
A27: TI / key money | B27: 0.15 | C27: 0 | D27: 0 | E27: 0.08 | F27: 0 | G27: 0 | H27: 0 | I27: Key money ÷ 10 yrs ÷ SF × 50% rent-equivalent ÷ normalized $/SF: 74A ≈16.2%, applied by the report as +15%; 17 S Edison ≈8.4% → +8% [28][50]. See check rows below.
A28: Net adjustment % | B28: =SUM(B16:B27) -> 0 | C28: =SUM(C16:C27) -> 0.18 | D28: =SUM(D16:D27) -> 0.23 | E28: =SUM(E16:E27) -> 0.13 | F28: =SUM(F16:F27) -> 0.14 | G28: =SUM(G16:G27) -> 0.11 | H28: =SUM(H16:H27) -> -0.08 | I28: SUM of the property adjustments above.
A29: Adjusted $/SF (NNN, ESTIMATE) | B29: =B14*(1+B28) -> 76.325088 | C29: =C14*(1+C28) -> 69.03 | D29: =D14*(1+D28) -> 49.463807 | E29: =E14*(1+E28) -> 61.365335 | F29: =F14*(1+F28) -> 47.590477 | G29: =G14*(1+G28) -> 83.25 | H29: =H14*(1+H28) -> 62.361081 | I29: Normalized $/SF × (1 + net adjustment). Range $47.59–$83.25 per report.
A31: CHECKS AGAINST THE REPORT
A32: Report normalized $/SF | B32: 76.33 | C32: 58.5 | D32: 40.21 | E32: 54.3 | F32: 41.75 | G32: 75 | H32: 67.78
A33: Difference (normalized, rounded to cents) | B33: =ROUND(B14,2)-B32 -> 0 | C33: =ROUND(C14,2)-C32 -> 0 | D33: =ROUND(D14,2)-D32 -> 0 | E33: =ROUND(E14,2)-E32 -> 0.01 | F33: =ROUND(F14,2)-F32 -> 0 | G33: =ROUND(G14,2)-G32 -> 0 | H33: =ROUND(H14,2)-H32 -> 0 | I33: Zero = reproduces the report (17 S Edison: $57.16 × 0.95 = $54.3056 → $54.31 vs report $54.30).
A34: Report adjusted $/SF | B34: 76.33 | C34: 69.03 | D34: 49.46 | E34: 61.36 | F34: 47.59 | G34: 83.25 | H34: 62.36
A35: Difference (adjusted, rounded to cents) | B35: =ROUND(B29,2)-B34 -> 0 | C35: =ROUND(C29,2)-C34 -> 0 | D35: =ROUND(D29,2)-D34 -> 0 | E35: =ROUND(E29,2)-E34 -> 0.01 | F35: =ROUND(F29,2)-F34 -> 0 | G35: =ROUND(G29,2)-G34 -> 0 | H35: =ROUND(H29,2)-H34 -> 0 | I35: Zero = reproduces the report. 17 S Edison +$0.01: report rounds normalized $/SF to $54.30 before applying +13% (unrounded chain gives $61.37); weighted result unaffected.
A37: WEIGHTING ATTRIBUTES (used by Market Rent Analysis, Method B)
A38: Tier | B38: ='Comparable Properties'!R5 -> 1 | C38: ='Comparable Properties'!R7 -> 2 | D38: ='Comparable Properties'!R12 -> 2 | E38: ='Comparable Properties'!R15 -> 3 | F38: ='Comparable Properties'!R14 -> 2 | G38: ='Comparable Properties'!R19 -> 3 | H38: ='Comparable Properties'!R25 -> 3
A39: Evidence status / grade (Method B category) | B39: Current B-grade ask | C39: Current B-grade ask | D39: Closed lease (unverified) | E39: Current B-grade ask | F39: Historical C-grade | G39: Current B-grade ask | H39: B-grade ask with internal conflict | I39: Category names must match the Evidence-grade weight table on Market Rent Analysis.
A40: Comparability score | B40: ='Comparable Properties'!Q5 -> 3 | C40: ='Comparable Properties'!Q7 -> 3 | D40: ='Comparable Properties'!Q12 -> 2 | E40: ='Comparable Properties'!Q15 -> 3 | F40: ='Comparable Properties'!Q14 -> 2 | G40: ='Comparable Properties'!Q19 -> 2 | H40: ='Comparable Properties'!Q25 -> 2
A41: Source grade (Comparable Properties) | B41: ='Comparable Properties'!P5 -> B | C41: ='Comparable Properties'!P7 -> B | D41: ='Comparable Properties'!P12 -> B | E41: ='Comparable Properties'!P15 -> B | F41: ='Comparable Properties'!P14 -> C | G41: ='Comparable Properties'!P19 -> B | H41: ='Comparable Properties'!P25 -> B (conflict)
A44: ASSUMPTIONS
A45: Size elasticity | C45: 0.15 | D45: Report: trophy spreads imply 0.3–0.6; 0.15 used because restaurant rent is driven by seats and back-of-house more than frontage [98].
A46: Key money: rent-equivalent share | C46: 0.5 | D46: Report assumption: 50% of key money is rent-equivalent; the other 50% pays for equipment and goodwill [28].
A47: 249 Main ground-floor SF | C47: 1000 | D47: Corcoran 2021 listing [47].
A48: 249 Main basement SF | C48: 1000 | D48: Corcoran 2021 listing [47].
A49: Basement weight in ground-equivalent SF | C49: 0.5 | D49: Report: basement counted at 50%.
A51: KEY-MONEY CHECK (formula-implied % vs the % the report applies)
A52: Item | B52: 74A Montauk Hwy | C52: 17 S Edison
A53: Key money ($, ASK) | B53: ='Comparable Properties'!B37 -> 700000 | C53: ='Comparable Properties'!B38 -> 250000
A54: Amortization years | B54: ='Comparable Properties'!$C$31 -> 10 | C54: ='Comparable Properties'!$C$31 -> 10
A55: SF | B55: =B8 -> 2830 | C55: =E8 -> 2729
A56: Key money $/SF/yr | B56: =B53/B54/B55 -> 24.734982 | C56: =C53/C54/C55 -> 9.1608648
A57: Rent-equivalent $/SF/yr (× share) | B57: =B56*$C$46 -> 12.367491 | C57: =C56*$C$46 -> 4.5804324
A58: Formula-implied % of normalized $/SF | B58: =B57/B14 -> 0.16203704 | C58: =C57/E14 -> 0.084345479
A59: % applied by the report (grid row) | B59: =B27 -> 0.15 | C59: =E27 -> 0.08
A60: Difference (implied − applied) | B60: =B58-B59 -> 0.012037037 | C60: =C58-C59 -> 0.0043454791
A61: Adjusted $/SF if implied % (rounded) were used | B61: =B14*(1+B28-B27+ROUND(B58,2)) -> 77.088339 | C61: =E14*(1+E28-E27+ROUND(C58,2)) -> 61.365335
A63: DISCREPANCY NOTE: for 74A the report computes $700,000 ÷ 10 ÷ 2,830 = $24.73/SF; × 50% = $12.37/SF, 'about 16% of the normalized $76.33, rounded to +15%'. This workbook keeps the report's +15% as an input so that it reproduces the report's $76.33 and $66.24; the strict formula value (≈16.2%, rounded 16%) would give the adjusted figure shown in row 61 (about $77.09) and raise the weighted result by about $0.24/SF. 17 S Edison's 8.4% rounds to the report's +8% (no discrepancy).
A65: NOTES & SOURCES
A66: Asking vs executed: most figures in this workbook are ASKING rents on listings, not executed leases. No executed Amagansett commercial rent is publicly disclosed for 2014–2026. The only closed Amagansett-ZIP food-service lease (2095 Montauk Hwy, closed 2025-06-08) is broker-reported and Compass flags its price 'Unverified' [42]. Asks are converted to an achieved basis with a moderate 5–10% discount (asks on market >180 days without a cut −10%; other asks −5%; closed 0%). Trophy village rows ($145–$240/SF) are excluded from the conclusion except as an outer ceiling.
A67: NNN assumption ($7.00/SF, range $5.00–$8.75; master input on Executive Summary): real estate taxes from broker-published tax bills run $1.38–$3.22/SF on small village commercial buildings [68][69][70][71]; the subject's own taxes are about $2.96/SF [3]; taxes alone at 74A are $4.92/SF [31]; the one stated all-in Amagansett NNN figure is $8.94/SF at 2095 Montauk Highway [42]; taxes at 136 Main / 11 Indian Wells run about $1.31–$2.02/SF [36]; and a generic national benchmark puts retail NNN at $4–$8/SF [72]. Insurance and maintenance components (about $1.00–$2.50 and $1.00–$3.00/SF respectively) are unsourced assumptions and should be replaced with the subject's actual figures.
A68: Labels: ASK = asking rent on a listing; EXECUTED/CLOSED = signed, assigned or broker-reported closed lease; HISTORICAL = dated past listing or event; BROKER OPINION = broker's quoted range; ESTIMATE = figure inferred or calculated in the report. Grades: A = government record or recorded transaction; B = broker listing with detailed terms or established real estate publication; C = historical listing, local newspaper or business website; D = aggregator, unverified database or search snippet.
A69: Source: '207 Main Street, Amagansett — Commercial Market Rent Assessment', effective 2026-10-07 (research/reports/207 Main Street Amagansett market rent.md). Bracketed numbers refer to the Sources tab, which lists every URL (all accessed 2026-10-07).

Sheet Market Rent Analysis
A1: Market Rent Analysis — Methods A, B and C, reconciliation and recommended range
A2: All $/SF are annual NNN base rent. Inputs in blue; formulas in black; links to other tabs in green.
A4: WEIGHT INPUTS (fixed before calculation, per report)
A5: Tier | B5: Tier weight | C5: Rationale
A6: 1 | B6: 3 | C6: Amagansett Main St / Montauk Hwy food service ~500–3,000 SF: closest to the subject's submarket and use
A7: 2 | B7: 2 | C7: Other Amagansett commercial
A8: 3 | B8: 1 | C8: Other Hamptons hamlets
A10: Evidence status / grade | B10: Evidence weight | C10: Rationale
A11: Closed lease (unverified) | B11: 1.25 | C11: Closed lease = 1.25, reduced from 1.5 because the 2095 price is flagged 'Unverified'
A12: Current B-grade ask | B12: 1 | C12: Current broker listing with detailed terms
A13: B-grade ask with internal conflict | B13: 0.75 | C13: 7 Hill St: unit page vs combined-unit page conflict
A14: Historical C-grade | B14: 0.5 | C14: Dated C-grade listing (249 Main, 2021)
A15: D-grade | B15: 0.25 | C15: None used as a weighted comparable
A16: Comparability score: 1 (weak) to 5 (near-identical), from Comparable Properties. Weight = tier weight × evidence weight × comparability score.
A18: METHOD A — DIRECT COMPARABLE ADJUSTED RANGE
A19: Measure | B19: All seven adjusted | C19: Score-3 subset | D19: Report
A20: Score threshold for direct-evidence subset | C20: 3 | D20: 74A, 11 IW 1st fl., 17 S Edison
A21: Low (MIN) | B21: =MIN(Adjustments!$B$29:$H$29) -> 47.590477 | C21: =_xlfn.MINIFS(Adjustments!$B$29:$H$29,Adjustments!$B$40:$H$40,$C$20) -> 61.365335 | D21: 61.36 | E21: All seven: $47.59
A22: Central (MEDIAN / mean) | B22: =MEDIAN(Adjustments!$B$29:$H$29) -> 62.361081 | C22: =AVERAGEIFS(Adjustments!$B$29:$H$29,Adjustments!$B$40:$H$40,$C$20) -> 68.906808 | D22: 68.91 | E22: All-seven median $62.36; score-3 mean $68.91
A23: High (MAX) | B23: =MAX(Adjustments!$B$29:$H$29) -> 83.25 | C23: =_xlfn.MAXIFS(Adjustments!$B$29:$H$29,Adjustments!$B$40:$H$40,$C$20) -> 76.325088 | D23: 76.33 | E23: All seven: $83.25
A24: Simple mean | B24: =AVERAGE(Adjustments!$B$29:$H$29) -> 64.19797 | D24: 64.2 | E24: Report: simple mean $64.20
A25: Method A conclusion (report): about $61–$76/SF, central tendency about $69 (score-3 comparables are the most direct evidence).
A27: METHOD B — WEIGHTED COMPARABLE (SUMPRODUCT)
A28: Comparable | B28: Adjusted $/SF | C28: Tier | D28: Tier wt. | E28: Evidence category | F28: Evidence wt. | G28: Score | H28: Weight | I28: Share | J28: Contribution
A29: =Adjustments!B6 -> Former Coche Comedor (annual option) | B29: =Adjustments!B29 -> 76.325088 | C29: =Adjustments!B38 -> 1 | D29: =INDEX($B$6:$B$8,MATCH(C29,$A$6:$A$8,0)) -> 3 | E29: =Adjustments!B39 -> Current B-grade ask | F29: =INDEX($B$11:$B$15,MATCH(E29,$A$11:$A$15,0)) -> 1 | G29: =Adjustments!B40 -> 3 | H29: =D29*F29*G29 -> 9 | I29: =H29/$H$36 -> 0.31578947 | J29: =I29*B29 -> 24.102659
A30: =Adjustments!C6 -> 11 Indian Wells Hwy, first floor | B30: =Adjustments!C29 -> 69.03 | C30: =Adjustments!C38 -> 2 | D30: =INDEX($B$6:$B$8,MATCH(C30,$A$6:$A$8,0)) -> 2 | E30: =Adjustments!C39 -> Current B-grade ask | F30: =INDEX($B$11:$B$15,MATCH(E30,$A$11:$A$15,0)) -> 1 | G30: =Adjustments!C40 -> 3 | H30: =D30*F30*G30 -> 6 | I30: =H30/$H$36 -> 0.21052632 | J30: =I30*B30 -> 14.532632
A31: =Adjustments!D6 -> 2095 Montauk Hwy restaurant | B31: =Adjustments!D29 -> 49.463807 | C31: =Adjustments!D38 -> 2 | D31: =INDEX($B$6:$B$8,MATCH(C31,$A$6:$A$8,0)) -> 2 | E31: =Adjustments!D39 -> Closed lease (unverified) | F31: =INDEX($B$11:$B$15,MATCH(E31,$A$11:$A$15,0)) -> 1.25 | G31: =Adjustments!D40 -> 2 | H31: =D31*F31*G31 -> 5 | I31: =H31/$H$36 -> 0.1754386 | J31: =I31*B31 -> 8.6778609
A32: =Adjustments!E6 -> 17 S Edison St restaurant | B32: =Adjustments!E29 -> 61.365335 | C32: =Adjustments!E38 -> 3 | D32: =INDEX($B$6:$B$8,MATCH(C32,$A$6:$A$8,0)) -> 1 | E32: =Adjustments!E39 -> Current B-grade ask | F32: =INDEX($B$11:$B$15,MATCH(E32,$A$11:$A$15,0)) -> 1 | G32: =Adjustments!E40 -> 3 | H32: =D32*F32*G32 -> 3 | I32: =H32/$H$36 -> 0.10526316 | J32: =I32*B32 -> 6.459509
A33: =Adjustments!F6 -> 249 Main St, Building B pop-up | B33: =Adjustments!F29 -> 47.590477 | C33: =Adjustments!F38 -> 2 | D33: =INDEX($B$6:$B$8,MATCH(C33,$A$6:$A$8,0)) -> 2 | E33: =Adjustments!F39 -> Historical C-grade | F33: =INDEX($B$11:$B$15,MATCH(E33,$A$11:$A$15,0)) -> 0.5 | G33: =Adjustments!F40 -> 2 | H33: =D33*F33*G33 -> 2 | I33: =H33/$H$36 -> 0.070175439 | J33: =I33*B33 -> 3.3396826
A34: =Adjustments!G6 -> 9 Railroad Ave | B34: =Adjustments!G29 -> 83.25 | C34: =Adjustments!G38 -> 3 | D34: =INDEX($B$6:$B$8,MATCH(C34,$A$6:$A$8,0)) -> 1 | E34: =Adjustments!G39 -> Current B-grade ask | F34: =INDEX($B$11:$B$15,MATCH(E34,$A$11:$A$15,0)) -> 1 | G34: =Adjustments!G40 -> 2 | H34: =D34*F34*G34 -> 2 | I34: =H34/$H$36 -> 0.070175439 | J34: =I34*B34 -> 5.8421053
A35: =Adjustments!H6 -> 7 Hill St (inline) | B35: =Adjustments!H29 -> 62.361081 | C35: =Adjustments!H38 -> 3 | D35: =INDEX($B$6:$B$8,MATCH(C35,$A$6:$A$8,0)) -> 1 | E35: =Adjustments!H39 -> B-grade ask with internal conflict | F35: =INDEX($B$11:$B$15,MATCH(E35,$A$11:$A$15,0)) -> 0.75 | G35: =Adjustments!H40 -> 2 | H35: =D35*F35*G35 -> 1.5 | I35: =H35/$H$36 -> 0.052631579 | J35: =I35*B35 -> 3.2821622
A36: Total | H36: =SUM(H29:H35) -> 28.5 | I36: =SUM(I29:I35) -> 1 | J36: =SUM(J29:J35) -> 66.236611
A37: Weighted average $/SF NNN (SUMPRODUCT ÷ SUM of weights) | B37: =SUMPRODUCT(B29:B35,H29:H35)/H36 -> 66.236611 | C37: Report | D37: 66.24 | E37: =ROUND(B37,2)-D37 -> 0 | F37: ← difference (0 = reproduces report; report weight total 28.5)
A39: METHOD B ROBUSTNESS (report: alternative assumptions move Method B between about $62.60 and $68.40)
A40: Scenario | B40: Alt. 74A $/SF | C40: Alt. 11 IW $/SF | D40: Weighted $/SF | E40: Report | F40: Difference
A41: Alt 1: 74A key money treated as entirely equipment (no key-money adjustment) | B41: =Adjustments!B14*(1+Adjustments!B28-Adjustments!B27) -> 64.876325 | C41: =B30 -> 69.03 | D41: =(SUMPRODUCT(B29:B35,H29:H35)-H29*B29+H29*B41)/H36 -> 62.621212 | E41: 62.62 | F41: =ROUND(D41,2)-E41 -> 0
A42: Alt 2: ask-to-achieved discount halved for 74A and 11 IW (−5% instead of −10%) | B42: =Adjustments!B11*(1+Adjustments!B12/2)*(1+Adjustments!B13)*(1+Adjustments!B28) -> 80.565371 | C42: =Adjustments!C11*(1+Adjustments!C12/2)*(1+Adjustments!C13)*(1+Adjustments!C28) -> 72.865 | D42: =(SUMPRODUCT(B29:B35,H29:H35)-H29*B29-H30*B30+H29*B42+H30*C42)/H36 -> 68.383016 | E42: 68.39 | F42: =ROUND(D42,2)-E42 -> -0.01 | G42: Formula gives $68.38 vs report $68.39: a $0.01 rounding difference, not fudged.
A44: METHOD C — DISTRIBUTION OF THE SEVEN ADJUSTED INDICATORS (QUARTILE, linear interpolation)
A45: Measure | B45: $/SF NNN | C45: Report | D45: Difference
A46: Low: 25th percentile | B46: =QUARTILE(Adjustments!$B$29:$H$29,1) -> 55.414571 | C46: 55.41 | D46: =ROUND(B46,2)-C46 -> 0
A47: Midpoint: median | B47: =QUARTILE(Adjustments!$B$29:$H$29,2) -> 62.361081 | C47: 62.36 | D47: =ROUND(B47,2)-C47 -> 0
A48: High: 75th percentile | B48: =QUARTILE(Adjustments!$B$29:$H$29,3) -> 72.677544 | C48: 72.68 | D48: =ROUND(B48,2)-C48 -> 0
A50: RECONCILIATION
A51: Method | B51: Low | C51: Central | D51: High | E51: Basis
A52: A: direct (score-3 comparables) | B52: =C21 -> 61.365335 | C52: =C22 -> 68.906808 | D52: =C23 -> 76.325088 | E52: Most direct evidence (74A, 11 IW, 17 S Edison)
A53: B: weighted (alternatives as low / high) | B53: =MIN(D41:D42) -> 62.621212 | C53: =$B$37 -> 66.236611 | D53: =MAX(D41:D42) -> 68.383016 | E53: Weighted result with robustness alternatives
A54: C: distribution | B54: =B46 -> 55.414571 | C54: =B47 -> 62.361081 | D54: =B48 -> 72.677544 | E54: Interquartile range and median of the seven indicators
A55: Reconciled ESTIMATE ($/SF NNN) | B55: 60 | C55: =ROUND($B$37,0) -> 66 | D55: 72
A56: Reconciliation judgment (report): LOW $60 (input) sits above Method C's 25th percentile ($55.41) because the two indicators below $50 (2095 Montauk, 249 Main) carry the largest normalizations, and just below Method A's lowest direct-evidence value ($61.36) to remain conservative. MIDPOINT = Method B rounded to the nearest dollar (formula). HIGH $72 (input) matches Method C's 75th percentile ($72.68) and sits below the 74A indicator ($76.33), which depends on an ask and a key-money allocation assumption. Low and high are appraiser judgments, not formula outputs; the checks below confirm they sit inside the method results.
A57: Check: low between Method C 25th pct and Method A low | B57: =AND(B55>=B46,B55<=C21) -> TRUE
A58: Check: high ≤ Method C 75th pct and < 74A indicator | B58: =AND(D55<=B48,D55<B29) -> TRUE
A60: RECOMMENDED MARKET RANGE AND IMPLIED SUBJECT RENT
A61: Measure | B61: Low | C61: Midpoint | D61: High | E61: Note
A62: $/SF/yr NNN base rent | B62: =$B$55 -> 60 | C62: =$C$55 -> 66 | D62: =$D$55 -> 72 | E62: Reconciled ESTIMATE
A63: Gross-equivalent $/SF/yr (+ NNN assumption) | B63: =B62+'Executive Summary'!$B$8 -> 67 | C63: =C62+'Executive Summary'!$B$8 -> 73 | D63: =D62+'Executive Summary'!$B$8 -> 79 | E63: Adds master NNN load
A64: Implied annual rent, subject (NNN) | B64: =B62*'Executive Summary'!$B$6 -> 66000 | C64: =C62*'Executive Summary'!$B$6 -> 72600 | D64: =D62*'Executive Summary'!$B$6 -> 79200 | E64: $/SF × subject SF
A65: Implied monthly rent, subject (NNN) | B65: =B64/12 -> 5500 | C65: =C64/12 -> 6050 | D65: =D64/12 -> 6600 | E65: Annual ÷ 12
A66: Gross-equivalent monthly | B66: =B63*'Executive Summary'!$B$6/12 -> 6141.6667 | C66: =C63*'Executive Summary'!$B$6/12 -> 6691.6667 | D66: =D63*'Executive Summary'!$B$6/12 -> 7241.6667
A67: Current monthly rent | B67: ='Executive Summary'!$B$7 -> 5000 | C67: ='Executive Summary'!$B$7 -> 5000 | D67: ='Executive Summary'!$B$7 -> 5000 | E67: Master input
A68: Current rent variance to market (NNN basis) | B68: =B67/B65-1 -> -0.090909091 | C68: =C67/C65-1 -> -0.17355372 | D68: =D67/D65-1 -> -0.24242424 | E68: Report: −9.1% / −17.4% / −24.2%
A69: Current $/SF vs gross-equivalent (if lease is gross) | B69: =('Executive Summary'!$B$7*12/'Executive Summary'!$B$6)/B63-1 -> -0.18588874 | C69: =('Executive Summary'!$B$7*12/'Executive Summary'!$B$6)/C63-1 -> -0.25280199 | D69: =('Executive Summary'!$B$7*12/'Executive Summary'!$B$6)/D63-1 -> -0.30955121 | E69: Report: about −25% at midpoint
A70: Net-equivalent (current $/SF − NNN) vs NNN market | B70: =('Executive Summary'!$B$7*12/'Executive Summary'!$B$6-'Executive Summary'!$B$8)/B62-1 -> -0.20757576 | C70: =('Executive Summary'!$B$7*12/'Executive Summary'!$B$6-'Executive Summary'!$B$8)/C62-1 -> -0.27961433 | D70: =('Executive Summary'!$B$7*12/'Executive Summary'!$B$6-'Executive Summary'!$B$8)/D62-1 -> -0.33964646 | E70: Report: about −28% at midpoint
A72: LANDLORD NEGOTIATING POSITIONS
A73: Position | B73: $/SF/yr (NNN) | C73: Monthly | D73: Annual | E73: Premium over current | F73: Gap: monthly | G73: Gap: annual | H73: Basis
A74: Conservative | B74: =$B$55 -> 60 | C74: =B74*'Executive Summary'!$B$6/12 -> 5500 | D74: =C74*12 -> 66000 | E74: =C74/'Executive Summary'!$B$7-1 -> 0.1 | F74: =C74-'Executive Summary'!$B$7 -> 500 | G74: =F74*12 -> 6000 | H74: Low end of reconciled range; just below the lowest score-3 comparable ($61.36)
A75: Fair market midpoint | B75: =$C$55 -> 66 | C75: =B75*'Executive Summary'!$B$6/12 -> 6050 | D75: =C75*12 -> 72600 | E75: =C75/'Executive Summary'!$B$7-1 -> 0.21 | F75: =C75-'Executive Summary'!$B$7 -> 1050 | G75: =F75*12 -> 12600 | H75: Method B weighted result ($66.24), rounded
A76: Aggressive | B76: =C76*12/'Executive Summary'!$B$6 -> 76.363636 | C76: =ROUND(Adjustments!B29*'Executive Summary'!$B$6/12,-2) -> 7000 | D76: =C76*12 -> 84000 | E76: =C76/'Executive Summary'!$B$7-1 -> 0.4 | F76: =C76-'Executive Summary'!$B$7 -> 2000 | G76: =F76*12 -> 24000 | H76: 74A Montauk Hwy adjusted indicator ($76.33), the only Tier 1 food-service comparable; monthly rounded to the nearest $100
A77: Term for cumulative gap (years) | B77: 5 | C77: Five-year midpoint gap, before escalations (ESTIMATE)
A78: Cumulative midpoint gap over term | B78: =G75*B77 -> 63000 | C78: Report: about $63,000
A80: DISCREPANCIES vs REPORT: (1) Method B robustness Alt 2 computes to $68.38 vs the report's $68.39 ($0.01 rounding). (1b) 17 S Edison: unrounded chain gives normalized $54.31 / adjusted $61.37 vs the report's $54.30 / $61.36 (report rounds at each step; no effect on $66.24). (1c) 74A seasonal annual-equivalent high computes to $92.29 vs $92.30 (Comparable Properties). (2) The report applies +15% for 74A key money although its own arithmetic gives ≈16.2%; the workbook keeps +15% (see Adjustments key-money check). Because of (1b), Method A's score-3 low shows $61.37 vs the report's $61.36. All other results reproduce the report to the cent: weighted $66.24; Method A high $76.33 and mean $68.91; Method C $55.41 / $62.36 / $72.68; reconciled $60 / $66 / $72; positions $5,500 / $6,050 / $7,000.
A82: NOTES & SOURCES
A83: Asking vs executed: most figures in this workbook are ASKING rents on listings, not executed leases. No executed Amagansett commercial rent is publicly disclosed for 2014–2026. The only closed Amagansett-ZIP food-service lease (2095 Montauk Hwy, closed 2025-06-08) is broker-reported and Compass flags its price 'Unverified' [42]. Asks are converted to an achieved basis with a moderate 5–10% discount (asks on market >180 days without a cut −10%; other asks −5%; closed 0%). Trophy village rows ($145–$240/SF) are excluded from the conclusion except as an outer ceiling.
A84: NNN assumption ($7.00/SF, range $5.00–$8.75; master input on Executive Summary): real estate taxes from broker-published tax bills run $1.38–$3.22/SF on small village commercial buildings [68][69][70][71]; the subject's own taxes are about $2.96/SF [3]; taxes alone at 74A are $4.92/SF [31]; the one stated all-in Amagansett NNN figure is $8.94/SF at 2095 Montauk Highway [42]; taxes at 136 Main / 11 Indian Wells run about $1.31–$2.02/SF [36]; and a generic national benchmark puts retail NNN at $4–$8/SF [72]. Insurance and maintenance components (about $1.00–$2.50 and $1.00–$3.00/SF respectively) are unsourced assumptions and should be replaced with the subject's actual figures.
A85: Labels: ASK = asking rent on a listing; EXECUTED/CLOSED = signed, assigned or broker-reported closed lease; HISTORICAL = dated past listing or event; BROKER OPINION = broker's quoted range; ESTIMATE = figure inferred or calculated in the report. Grades: A = government record or recorded transaction; B = broker listing with detailed terms or established real estate publication; C = historical listing, local newspaper or business website; D = aggregator, unverified database or search snippet.
A86: Source: '207 Main Street, Amagansett — Commercial Market Rent Assessment', effective 2026-10-07 (research/reports/207 Main Street Amagansett market rent.md). Bracketed numbers refer to the Sources tab, which lists every URL (all accessed 2026-10-07).

Sheet Sensitivity Analysis
A1: Sensitivity Analysis
A2: All formulas run off the master SF, current rent and NNN inputs on Executive Summary. Market $/SF values are NNN base rent.
A4: TABLE 1 — IMPLIED RENT FOR THE SUBJECT AT ALTERNATIVE MARKET RATES
A5: Subject SF (master) | B5: ='Executive Summary'!$B$6 -> 1100 | C5: Current monthly rent (master) | D5: ='Executive Summary'!$B$7 -> 5000
A6: $/SF/yr (NNN) | B6: Annual rent | C6: Monthly rent | D6: Change vs current monthly | E6: Position vs reconciled range
A7: 50 | B7: =A7*$B$5 -> 55000 | C7: =B7/12 -> 4583.3333 | D7: =C7/$D$5-1 -> -0.083333333 | E7: =IF(A7<'Market Rent Analysis'!$B$55,"Below range",IF(A7>'Market Rent Analysis'!$D$55,"Above range","Within range")) -> Below range
A8: 55 | B8: =A8*$B$5 -> 60500 | C8: =B8/12 -> 5041.6667 | D8: =C8/$D$5-1 -> 0.0083333333 | E8: =IF(A8<'Market Rent Analysis'!$B$55,"Below range",IF(A8>'Market Rent Analysis'!$D$55,"Above range","Within range")) -> Below range
A9: 60 | B9: =A9*$B$5 -> 66000 | C9: =B9/12 -> 5500 | D9: =C9/$D$5-1 -> 0.1 | E9: =IF(A9<'Market Rent Analysis'!$B$55,"Below range",IF(A9>'Market Rent Analysis'!$D$55,"Above range","Within range")) -> Within range
A10: 65 | B10: =A10*$B$5 -> 71500 | C10: =B10/12 -> 5958.3333 | D10: =C10/$D$5-1 -> 0.19166667 | E10: =IF(A10<'Market Rent Analysis'!$B$55,"Below range",IF(A10>'Market Rent Analysis'!$D$55,"Above range","Within range")) -> Within range
A11: 70 | B11: =A11*$B$5 -> 77000 | C11: =B11/12 -> 6416.6667 | D11: =C11/$D$5-1 -> 0.28333333 | E11: =IF(A11<'Market Rent Analysis'!$B$55,"Below range",IF(A11>'Market Rent Analysis'!$D$55,"Above range","Within range")) -> Within range
A12: 75 | B12: =A12*$B$5 -> 82500 | C12: =B12/12 -> 6875 | D12: =C12/$D$5-1 -> 0.375 | E12: =IF(A12<'Market Rent Analysis'!$B$55,"Below range",IF(A12>'Market Rent Analysis'!$D$55,"Above range","Within range")) -> Above range
A13: 80 | B13: =A13*$B$5 -> 88000 | C13: =B13/12 -> 7333.3333 | D13: =C13/$D$5-1 -> 0.46666667 | E13: =IF(A13<'Market Rent Analysis'!$B$55,"Below range",IF(A13>'Market Rent Analysis'!$D$55,"Above range","Within range")) -> Above range
A14: 85 | B14: =A14*$B$5 -> 93500 | C14: =B14/12 -> 7791.6667 | D14: =C14/$D$5-1 -> 0.55833333 | E14: =IF(A14<'Market Rent Analysis'!$B$55,"Below range",IF(A14>'Market Rent Analysis'!$D$55,"Above range","Within range")) -> Above range
A15: 90 | B15: =A15*$B$5 -> 99000 | C15: =B15/12 -> 8250 | D15: =C15/$D$5-1 -> 0.65 | E15: =IF(A15<'Market Rent Analysis'!$B$55,"Below range",IF(A15>'Market Rent Analysis'!$D$55,"Above range","Within range")) -> Above range
A16: 100 | B16: =A16*$B$5 -> 110000 | C16: =B16/12 -> 9166.6667 | D16: =C16/$D$5-1 -> 0.83333333 | E16: =IF(A16<'Market Rent Analysis'!$B$55,"Below range",IF(A16>'Market Rent Analysis'!$D$55,"Above range","Within range")) -> Above range
A17: Current rent implied $/SF | B17: =D5*12/B5 -> 54.545455 | C17: Current rent is at market only if market rent ≈ this level (report: about $55/SF).
A19: TABLE 2 — CURRENT $/SF AND GAP TO MARKET AT ALTERNATIVE BUILDING AREAS
A20: Building area (SF) | B20: Current $/SF/yr | C20: Market monthly at low | D20: Market monthly at midpoint | E20: Market monthly at high | F20: Current vs market midpoint | G20: Current vs market low
A21: 1000 | B21: =$D$5*12/A21 -> 60 | C21: ='Market Rent Analysis'!$B$55*A21/12 -> 5000 | D21: ='Market Rent Analysis'!$C$55*A21/12 -> 5500 | E21: ='Market Rent Analysis'!$D$55*A21/12 -> 6000 | F21: =$D$5/D21-1 -> -0.090909091 | G21: =$D$5/C21-1 -> 0
A22: 1100 | B22: =$D$5*12/A22 -> 54.545455 | C22: ='Market Rent Analysis'!$B$55*A22/12 -> 5500 | D22: ='Market Rent Analysis'!$C$55*A22/12 -> 6050 | E22: ='Market Rent Analysis'!$D$55*A22/12 -> 6600 | F22: =$D$5/D22-1 -> -0.17355372 | G22: =$D$5/C22-1 -> -0.090909091
A23: 1200 | B23: =$D$5*12/A23 -> 50 | C23: ='Market Rent Analysis'!$B$55*A23/12 -> 6000 | D23: ='Market Rent Analysis'!$C$55*A23/12 -> 6600 | E23: ='Market Rent Analysis'!$D$55*A23/12 -> 7200 | F23: =$D$5/D23-1 -> -0.24242424 | G23: =$D$5/C23-1 -> -0.16666667
A24: Area is the single most sensitive unverified input (1,100 SF rests on a 2016 broker listing and a memoir). At ~1,000 SF the current rent sits at the market low (marginally less gap after the size elasticity raises market $/SF ~1.4% for a smaller space); at 1,200 SF the gap widens to about 24%.
A26: TABLE 3 — NNN vs GROSS EFFECT (gross-equivalent $/SF at NNN load low / base / high)
A27: NNN load scenario | B27: NNN load $/SF/yr | C27: Gross-equiv. low $/SF | D27: Gross-equiv. midpoint $/SF | E27: Gross-equiv. high $/SF | F27: Gross-equiv. monthly at midpoint | G27: Current $/SF vs gross-equiv. midpoint | H27: If gross: net-equiv. $/SF
A28: Low | B28: 5 | C28: ='Market Rent Analysis'!$B$55+B28 -> 65 | D28: ='Market Rent Analysis'!$C$55+B28 -> 71 | E28: ='Market Rent Analysis'!$D$55+B28 -> 77 | F28: =D28*$B$5/12 -> 6508.3333 | G28: =$B$17/D28-1 -> -0.23175416 | H28: =$B$17-B28 -> 49.545455
A29: Base (master input) | B29: ='Executive Summary'!$B$8 -> 7 | C29: ='Market Rent Analysis'!$B$55+B29 -> 67 | D29: ='Market Rent Analysis'!$C$55+B29 -> 73 | E29: ='Market Rent Analysis'!$D$55+B29 -> 79 | F29: =D29*$B$5/12 -> 6691.6667 | G29: =$B$17/D29-1 -> -0.25280199 | H29: =$B$17-B29 -> 47.545455
A30: High | B30: 8.75 | C30: ='Market Rent Analysis'!$B$55+B30 -> 68.75 | D30: ='Market Rent Analysis'!$C$55+B30 -> 74.75 | E30: ='Market Rent Analysis'!$D$55+B30 -> 80.75 | F30: =D30*$B$5/12 -> 6852.0833 | G30: =$B$17/D30-1 -> -0.27029492 | H30: =$B$17-B30 -> 45.795455
A31: NNN load range $5.00–$8.75/SF per report (taxes $1.38–$3.22/SF on small village buildings, subject ~$2.96/SF, one stated all-in Amagansett NNN $8.94/SF; insurance and maintenance unsourced). Lease type is the second most sensitive unknown: if the $5,000 is gross, the current $54.55/SF compares with a gross-equivalent midpoint of $73/SF (about 25% below).

Sheet Sources
A1: Sources / URLs (all accessed 2026-10-07)
A2: Parsed from the report's Sources list. Bracketed numbers on every tab refer to this list.
A4: # | B4: Source | C4: URL | D4: Grade
A5: 1 | B5: NYS ORPTS Property Assessment Data, parcel 171.-1-18 (roll years 2021–2025) | C5: https://data.ny.gov/resource/7vem-aaz7.json?$where=swis_code=%27472489%27%20AND%20print_key_code=%27171.-1-18%27 | D5: A.
A6: 2 | B6: NYS ORPTS Property Assessment Data, dataset 7vem-aaz7 (block 171-1, 2025 roll) | C6: https://data.ny.gov/resource/7vem-aaz7.json | D6: A.
A7: 3 | B7: PropertyShark, 207 Main St, Amagansett | C7: https://www.propertyshark.com/mason/Property/33812847/207-Main-St-Amagansett-NY-11930/ | D7: D.
A8: 4 | B8: Town of East Hampton Code ch. 255, Appendix A, Amagansett Historic District Guidelines | C8: https://ecode360.com/10416540 | D8: A.
A9: 5 | B9: Town of East Hampton Code § 255-11-10, Use Table for Commercial Uses (2018) | C9: https://ecode360.com/attachment/EA0658/EA0658-255c%20Use%20Table%20-%20Commercial.pdf | D9: A.
A10: 6 | B10: Town of East Hampton Code ch. 255, Attachment 5, Dimensional Regulations | C10: https://ecode360.com/attachment/EA0658/EA0658-255e%20Business%20Commercial%20Industrial%20-%20Dimensional%20Regs.pdf | D10: A.
A11: 7 | B11: Town of East Hampton Planning Dept., ARB Evaluation, 177 Main St (2023-07-10) | C11: https://www.ehamptonny.gov/AgendaCenter/ViewFile/Item/2157?fileID=5624 | D11: A.
A12: 8 | B12: Suffolk County Planning Commission staff report, East Hampton hamlet reports (2020) | C12: https://suffolkcountyny.gov/Portals/0/formsdocs/planning/scplanningcommission/2020/Staff%20Report%20Town%20of%20East%20Hampton%20-%20Comp%20Plan%20amendment%20East%20Hampton%20Hamlet%20Reports%20Amagansett%20a.pdf | D12: A.
A13: 9 | B13: Patch, Mary's Marvelous Amagansett to close; new tenant sought (2016-12-08) | C13: https://patch.com/new-york/riverhead/marys-marvelous-amagansett-close-new-tenant-sought | D13: B.
A14: 10 | B14: 27east, Mary's Marvelous in Amagansett to close when new tenant is found (2016-12-09) | C14: https://www.27east.com/real-estate-news/marys-marvelous-in-amagansett-to-close-when-new-tenant-is-found-1404430 | D14: B.
A15: 11 | B15: Dan's Papers, Mary's Marvelous closing and available to lease (2016-12-09) | C15: https://www.danspapers.com/2016/12/marys-marvelous-in-amagansett-closing-and-available-to-lease/ | D15: C.
A16: 12 | B16: Behind the Hedges, Mary's Marvelous closing and available to lease (2016-12-09) | C16: https://behindthehedges.com/marys-marvelous-in-amagansett-closing-and-available-to-lease/ | D16: B.
... A135: 131 | B135: East Hampton Star, Poxy: third time a charm? (2011-01-21) | C135: https://www.easthamptonstar.com/archive/poxy-third-time-charm | D135: C.
